Workbook

Sheet 📖 HOW TO USE
A1: 📖 HOW TO USE — TRUE SINGLE ENTRY SYSTEM
A2: One entry in ONE sheet updates ALL related sheets automatically
A4: WHAT IS SINGLE ENTRY?
A5: You enter data in ONE place only. All other sheets (Receivables, Bank Book, Cash Book, P&L, Balance Sheet, Dashboard) automatically read from that single source using formulas. You NEVER enter the same data twice.
A7: THE 4 DATA ENTRY POINTS (Everything else is AUTO)
A8: 1. 💳 PAYMENTS ← Enter Here → Receipt No. auto-generates | Customer Name auto-fills | Flat ID auto-fills | Bank/Cash Book auto-updates | Receivables auto-updates | P&L auto-updates | Dashboard auto-updates
A9: 2. 🧾 EXPENSES ← Enter Here → Voucher No. auto-generates | Bank/Cash auto-deducts | GL auto-posts | Trial Balance auto-updates | P&L auto-updates | Balance Sheet auto-updates
A10: 3. 📦 PURCHASES ← Enter Here → Vendor Name auto-fills | Material Name auto-fills | Inventory auto-increases | Vendor Payable auto-increases | GL auto-posts
A11: 4. 🏗️ Site Log → Material consumption auto-reduces inventory | Contractor bill auto-updates payables
A13: MASTER DATA (Set up once, never re-enter)
A14: 🏘️ Flat Master → Add each flat once. Set Status=Sold and Customer ID to auto-generate the full installment schedule.
A15: 👤 Customers → Add each buyer once. Sale value, paid amount, outstanding all calculate automatically.
... A48: 🔵 Blue text = Formula cell — never overwrite

Sheet 📊 DASHBOARD
A1: 📊 PROPERTY & CONSTRUCTION ERP — EXECUTIVE DASHBOARD
A2: Single Entry System | Marora Residency | Live as of 15 July 2026
A3: ▶ 📖 How To Use | E3: ▶ 🏘️ Flat Master | I3: ▶ 💳 ENTER PAYMENT | M3: ▶ 🧾 ENTER EXPENSE | Q3: ▶ 📦 ENTER PURCHASE | U3: ▶ 📅 Installments
A5: ▌ PROJECT STATUS
A6: Total Units | E6: ✅ Sold | I6: 🔵 Available | M6: 🟡 Hold/Booked | Q6: ❌ Cancelled | U6: 🏗️ Projects
A7: =COUNTA('🏘️ Flat Register'!A8:A4992) -> 11 | E7: =COUNTIF('🏘️ Flat Register'!L:L,"Sold") -> 1 | I7: =COUNTIF('🏘️ Flat Register'!L:L,"Available") -> 8 | M7: =COUNTIF('🏘️ Flat Register'!L:L,"Hold")+COUNTIF('🏘️ Flat Register'!L:L,"Booked") -> 2 | Q7: =COUNTIF('🏘️ Flat Register'!L:L,"Cancelled") -> 0 | U7: =COUNTA('🏗️ Projects'!A4:A500) -> 1
A9: ▌ FINANCIAL SNAPSHOT — All from single entries in Payments & Expenses
A10: 💰 Total Sales Value | G10: 📥 Total Collected | M10: 📤 Outstanding | S10: 📊 Collection %
A11: =SUMIF('🏘️ Flat Register'!L:L,"Sold",'🏘️ Flat Register'!H:H) -> 5670000 | G11: =SUM('💳 PAYMENTS Entery'!H11:H49967) -> 2580000 | M11: =D10-J10 -> 0 | S11: =IFERROR(J10/D10,0) -> 0
A13: ▌ CASH & BANK POSITION — Auto from single expense/payment entries
A14: 🏦 Bank Balance | G14: 💵 Cash Balance | M14: 💸 Total Expenses | S14: 📈 Net Profit
A15: ='🏦 Bank Book AUTO'!E12 -> -3315000 | G15: ='💵 Cash Book AUTO'!D7 -> 1835000 | M15: =SUM('🧾 EXPENSES ← Enter Here'!J11:J50000) -> 4060000 | S15: ='📊 P&L AUTO'!H29 -> 1610000
A17: ▌ INSTALLMENT ALERTS — Auto from Installments sheet
A18: 🔴 Overdue Inst. | G18: ⏳ Pending Inst. | M18: 💰 Overdue Amount | S18: 📦 LOW STOCK Items
A19: =COUNTIF('📅 Installments AUTO'!N:N,"Overdue") -> 2 | G19: =COUNTIF('📅 Installments AUTO'!N:N,"Pending") -> 8 | M19: =SUMIF('📅 Installments AUTO'!N:N,"Overdue",'📅 Installments AUTO'!K:K) -> 1150000 | S19: =COUNTIF('📦 Materials'!K:K,"LOW STOCK") -> 4
A21: ▌ RECEIVABLES AGING — Auto from single payment entries
A22: Customer | B22: Flat | C22: Sale Value (PKR) | D22: Received (PKR) | E22: Outstanding (PKR) | F22: 0-30 Days | G22: 31-60 Days | H22: >60 Days | I22: % Collected | J22: Priority | K22: Status
A23: =IFERROR(VLOOKUP('📋 Receivables AUTO'!B9,'👤 Customers'!A:C,2,0),"") -> AB-Sachal-GH/2024/1/2024 | B23: ='📋 Receivables AUTO'!A9 -> 101 | C23: ='📋 Receivables AUTO'!D9 -> 3915000 | D23: ='📋 Receivables AUTO'!E9 -> 0 | E23: ='📋 Receivables AUTO'!F9 -> 3915000 | F23: ='📋 Receivables AUTO'!G9 -> 0 | G23: ='📋 Receivables AUTO'!H9 -> 0 | H23: ='📋 Receivables AUTO'!I9+'📋 Receivables AUTO'!J9 -> 0 | I23: ='📋 Receivables AUTO'!K9 -> 0 | J23: ='📋 Receivables AUTO'!N9 -> MED | K23: =IF('📋 Receivables AUTO'!F9>0,IF('📋 Receivables AUTO'!G9+'📋 Receivables AUTO'!H9>0,"OVERDUE","PENDING"),"CLEAR") -> PENDING
A24: =IFERROR(VLOOKUP('📋 Receivables AUTO'!B10,'👤 Customers'!A:C,2,0),"") -> AB-Sachal-GH/2024/2/2024 | B24: ='📋 Receivables AUTO'!A10 -> 202 | C24: ='📋 Receivables AUTO'!D10 -> 5670000 | D24: ='📋 Receivables AUTO'!E10 -> 2430000 | E24: ='📋 Receivables AUTO'!F10 -> 3240000 | F24: ='📋 Receivables AUTO'!G10 -> 0 | G24: ='📋 Receivables AUTO'!H10 -> 0 | H24: ='📋 Receivables AUTO'!I10+'📋 Receivables AUTO'!J10 -> 0 | I24: ='📋 Receivables AUTO'!K10 -> 0.42857143 | J24: ='📋 Receivables AUTO'!N10 -> MED | K24: =IF('📋 Receivables AUTO'!F10>0,IF('📋 Receivables AUTO'!G10+'📋 Receivables AUTO'!H10>0,"OVERDUE","PENDING"),"CLEAR") -> PENDING
A26: ▌ EXPENSE BREAKDOWN — Auto from single expense entries
A27: Category | B27: Amount (PKR) | C27: % of Total
A28: Material | B28: =IFERROR(SUMIF('🧾 EXPENSES ← Enter Here'!E:E,"Material",'🧾 EXPENSES ← Enter Here'!J:J),0) -> 0 | C28: =IFERROR(B28/SUM($B$28:$B$33),0) -> 0
A29: Labor | B29: =IFERROR(SUMIF('🧾 EXPENSES ← Enter Here'!E:E,"Labor",'🧾 EXPENSES ← Enter Here'!J:J),0) -> 0 | C29: =IFERROR(B29/SUM($B$28:$B$33),0) -> 0
A30: Contractor | B30: =IFERROR(SUMIF('🧾 EXPENSES ← Enter Here'!E:E,"Contractor",'🧾 EXPENSES ← Enter Here'!J:J),0) -> 0 | C30: =IFERROR(B30/SUM($B$28:$B$33),0) -> 0
A31: Admin | B31: =IFERROR(SUMIF('🧾 EXPENSES ← Enter Here'!E:E,"Admin",'🧾 EXPENSES ← Enter Here'!J:J),0) -> 0 | C31: =IFERROR(B31/SUM($B$28:$B$33),0) -> 0
A32: Marketing | B32: =IFERROR(SUMIF('🧾 EXPENSES ← Enter Here'!E:E,"Marketing",'🧾 EXPENSES ← Enter Here'!J:J),0) -> 0 | C32: =IFERROR(B32/SUM($B$28:$B$33),0) -> 0
A33: Other | B33: =IFERROR(SUMIF('🧾 EXPENSES ← Enter Here'!E:E,"Other",'🧾 EXPENSES ← Enter Here'!J:J),0) -> 4060000 | C33: =IFERROR(B33/SUM($B$28:$B$33),0) -> 1
A34: TOTAL EXPENSES | B34: =SUM(B28:B33) -> 4060000 | C34: 100%
A36: ▌ PARTNER & CONSTRUCTION STATUS
A37: 👥 Ahmed Profit Share | G37: 👥 Taufeeq Profit Share | M37: 🏗️ Construction % | S37: 📤 Vendor Payables
A38: =IFERROR('📊 P&L AUTO'!H29*0.5,0) -> 805000 | G38: =IFERROR('📊 P&L AUTO'!H29*0.5,0) -> 805000 | M38: =IFERROR(MAX('🏗️ Site Log'!J4:J500),0) -> 0.15 | S38: =IFERROR(SUM('📤 Payables AUTO'!F6:F500),0) -> 0

Sheet 🏗️ Projects
A1: 🏗️ PROJECT MASTER
A2: Budget | Timeline | Live Spend from Expenses
A3: Project ID | B3: Name | C3: Type | D3: Location | E3: Start | F3: Target End | G3: Budget (PKR) | H3: Actual Spend [AUTO] | I3: Variance [AUTO] | J3: % Spent [AUTO] | K3: Units [AUTO] | L3: Sold [AUTO] | M3: Revenue [AUTO] | N3: Manager | O3: Status
A4: PRJ-001 | B4: Marora Residency | C4: Residential | D4: Marora Town | E4: 15-01-2026 | F4: 46752 | G4: 250000000 | H4: =IFERROR(SUMIF('🧾 EXPENSES ← Enter Here'!D:D,A4,'🧾 EXPENSES ← Enter Here'!J:J),0) -> 4000000 | I4: =G4-H4 -> 246000000 | J4: =IFERROR(H4/G4,0) -> 0.016 | K4: =IFERROR(COUNTIF('🏘️ Flat Register'!B:B,A4),0) -> 11 | L4: =IFERROR(COUNTIFS('🏘️ Flat Register'!B:B,A4,'🏘️ Flat Register'!L:L,"Sold"),0) -> 1 | M4: =IFERROR(SUMIFS('🏘️ Flat Register'!H:H,'🏘️ Flat Register'!B:B,A4,'🏘️ Flat Register'!L:L,"Sold"),0) -> 5670000 | N4: Ahmed Malik | O4: Active

Sheet 👥 Partners
A1: 👥 PARTNER MASTER — Capital | Profit Ratio | Auto Profit Share
A2: N
A3: Total Capital | D3: Net Profit | G3: Withdrawals | J3: Net Equity
A4: =SUM(F8:F12) -> 2000000 | D4: ='📊 P&L AUTO'!H32 -> 1610000 | G4: =SUM(I8:I12) -> 0 | J4: =A4+D4-G4 -> 3610000
A6: PARTNER REGISTER
A7: Partner ID | B7: Partner Name | C7: Father/Guardian | D7: CNIC | E7: Mobile | F7: Capital (PKR) | G7: Profit % | H7: Profit Share (PKR) | I7: Withdrawals (PKR) | J7: Balance (PKR) | K7: Bank Account | L7: Bank | M7: Join Date | N7: Status | O7: Notes
A8: P-002 | B8: sharjeel ahmed | C8: Taufeeq Ahmed | D8: 42101-0000002-2 | E8: 03002222222 | F8: =SUMIFS(F15:F39,E15:E39,E15,D15:D39,D15) -> 1000000 | G8: 0.5 | H8: =IFERROR('[1]📊 P&L'!H32*G8,0) -> 12050000 | I8: =SUMIFS(F15:F39,E15:E39,"Withdrawals",D15:D39,D15) -> 0 | J8: =F8+H8-I8 -> 13050000 | K8: 0987-6543210 | L8: HBL | M8: 46157 | N8: Active | O8: Lead Partner
A9: P-003 | B9: Faraz Gulzar | C9: Gulzar Soomro | D9: 42101-0000002-2 | E9: 03002222222 | F9: =SUMIFS(F16:F40,E16:E40,E16,D16:D40,D16) -> 1000000 | G9: 0.5 | H9: =IFERROR('[1]📊 P&L'!H32*G9,0) -> 12050000 | I9: =SUMIFS(F16:F40,E16:E40,"Withdrawals",D16:D40,D16) -> 0 | J9: =F9+H9-I9 -> 13050000 | K9: 0987-6543210 | L9: Meezan bank | M9: 46157 | N9: Active | O9: Active Partner
A13: CONTRIBUTION LOG
A14: Txn ID | B14: Date | C14: Partner ID | D14: Partner Name | E14: Type | F14: Amount (PKR) | G14: Bank | H14: Ref No. | I14: Approved By | J14: Notes | K14: Source
A15: PC-001 | B15: 46156 | C15: P-002 | D15: =IFERROR(VLOOKUP(C15,'[1]👥 Partners'!A:B,2,0),"") -> sharjeel ahmed | E15: Capital Injection | F15: 1000000 | G15: HBL | H15: CHQ-002 | I15: Sharjeel Ahmed | J15: Initial capital | K15: Al Gulzar Heights profit
A16: PC-002 | B16: 46156 | C16: P-003 | D16: =IFERROR(VLOOKUP(C16,'[1]👥 Partners'!A:B,2,0),"") -> Faraz Gulzar | E16: Capital Injection | F16: 1000000 | G16: Meezan | H16: CHQ-003 | I16: Sharjeel Ahmed | J16: Initial capital | K16: Al Gulzar Heights profit

Sheet 🏘️ Flat Register
A1: 🏘️ FLAT REGISTER — Master Inventory
A2: Enter each flat ONCE. All other sheets read from here.
A3: Total Units | E3: Sold | I3: Available | L3: Possesion Given | O3: Cancelled | R3: Total Sale Value | T3: Total Collected | V3: Outstanding
A4: =COUNTA(A7:A4992)-0 -> 12 | E4: =COUNTIF(L7:L4992,"Sold")++COUNTIF(L7:L4992,"Booked") -> 2 | I4: =COUNTIF(L7:L4992,"Available") -> 8 | L4: =COUNTIF(L7:L4992,"Possession Given") -> 0 | O4: =COUNTIF(L7:L4992,"Cancelled") -> 0 | R4: =SUMIF(L7:L4992,"Sold",H7:H4992) -> 5670000 | T4: =SUM(S8:S18) -> 2430000 | V4: =R4-T4 -> 3240000
A6: ▌ UNIT REGISTER — Enter each flat once. Change Status to Sold when booking confirmed.
A7: Flat ID | B7: Project ID | C7: Type | D7: Floor | E7: Flat No. | F7: Area sqft | G7: Price/sqft | H7: Total Price [AUTO} | I7: Extra Charges | J7: Discount | K7: Net Price [AUTO] | L7: Status [ENTER] | M7: Customer ID | N7: Customer Name [AUTO] | O7: Booking Date | P7: Pay Plan | Q7: Installments [AUTO] | R7: Inst. Paid | S7: Collected [AUTO] | T7: Outstanding [AUTO] | U7: Last Pay [AUTO] | V7: % Collected [AUTO] | W7: Completion Date | X7: Possession Date | Y7: Notes
A8: 1 | B8: PRJ-001 | C8: B | D8: Ground | E8: 1 | F8: 468 | G8: 7500 | H8: =G8*F8 -> 3510000 | K8: =H8+I8-J8 -> 3510000 | L8: Available | M8: =IFERROR(INDEX('👤 Customers'!$A$5:$A$100,MATCH(A8,'👤 Customers'!$K$5:$K$100,0)),"") -> C-003 | N8: =IFERROR(VLOOKUP(M8,'👤 Customers'!A:C,3,0),"") -> hello | O8: =IFERROR(VLOOKUP(M8,'👤 Customers'!A:T,19,0),"") -> 46218 | Q8: =IFERROR(COUNTIF('📅 Installments AUTO'!C:C,A8),0) -> 0 | R8: =IFERROR(COUNTIFS('📅 Installments AUTO'!C:C,A8,'📅 Installments AUTO'!N:N,"Paid"),0) -> 0 | S8: =IFERROR(SUMIF('💳 PAYMENTS Entery'!G:G,A8,'💳 PAYMENTS Entery'!H:H),0) -> 0 | T8: =H8-S8 -> 3510000 | U8: =IFERROR(MAXIFS('💳 PAYMENTS Entery'!C:C,'💳 PAYMENTS Entery'!G:G,A8),"") | V8: =IFERROR(S8/H8,0) -> 0 | W8: 31-12-2027 | X8: 31-12-2027 | Y8: Corner unit
A9: 2 | B9: PRJ-001 | C9: A | D9: Ground | E9: 2 | F9: 702 | G9: 7500 | H9: =G9*F9 -> 5265000 | K9: =H9+I9-J9 -> 5265000 | L9: Hold | M9: =IFERROR(INDEX('👤 Customers'!$A$5:$A$100,MATCH(A9,'👤 Customers'!$K$5:$K$100,0)),"") | N9: =IFERROR(VLOOKUP(M9,'👤 Customers'!A:C,3,0),"") | O9: 46054 | Q9: =IFERROR(COUNTIF('📅 Installments AUTO'!C:C,A9),0) -> 0 | R9: =IFERROR(COUNTIFS('📅 Installments AUTO'!C:C,A9,'📅 Installments AUTO'!N:N,"Paid"),0) -> 0 | S9: =IFERROR(SUMIF('💳 PAYMENTS Entery'!G:G,A9,'💳 PAYMENTS Entery'!H:H),0) -> 0 | T9: =H9-S9 -> 5265000 | U9: =IFERROR(MAXIFS('💳 PAYMENTS Entery'!C:C,'💳 PAYMENTS Entery'!G:G,A9),"") | V9: =IFERROR(S9/H9,0) -> 0
A10: 101 | B10: PRJ-001 | C10: B | D10: 1st | E10: 101 | F10: 522 | G10: 7500 | H10: =G10*F10 -> 3915000 | K10: =H10+I10-J10 -> 3915000 | L10: Available | M10: =IFERROR(INDEX('👤 Customers'!$A$5:$A$100,MATCH(A10,'👤 Customers'!$K$5:$K$100,0)),"") -> C-002 | N10: =IFERROR(VLOOKUP(M10,'👤 Customers'!A:C,3,0),"") -> Sharjeel | Q10: =IFERROR(COUNTIF('📅 Installments AUTO'!C:C,A10),0) -> 0 | R10: =IFERROR(COUNTIFS('📅 Installments AUTO'!C:C,A10,'📅 Installments AUTO'!N:N,"Paid"),0) -> 0 | S10: =IFERROR(SUMIF('💳 PAYMENTS Entery'!G:G,A10,'💳 PAYMENTS Entery'!H:H),0) -> 0 | T10: =H10-S10 -> 3915000 | U10: =IFERROR(MAXIFS('💳 PAYMENTS Entery'!C:C,'💳 PAYMENTS Entery'!G:G,A10),"") | V10: =IFERROR(S10/H10,0) -> 0
A11: 102 | B11: PRJ-001 | C11: A | D11: 1st | E11: 102 | F11: 756 | G11: 7500 | H11: =G11*F11 -> 5670000 | I11: 0 | J11: 0 | K11: =H11+I11-J11 -> 5670000 | L11: Available | M11: =IFERROR(INDEX('👤 Customers'!$A$5:$A$100,MATCH(A11,'👤 Customers'!$K$5:$K$100,0)),"") | N11: =IFERROR(VLOOKUP(M11,'👤 Customers'!A:C,3,0),"") | Q11: =IFERROR(COUNTIF('📅 Installments AUTO'!C:C,A11),0) -> 0 | R11: =IFERROR(COUNTIFS('📅 Installments AUTO'!C:C,A11,'📅 Installments AUTO'!N:N,"Paid"),0) -> 0 | S11: =IFERROR(SUMIF('💳 PAYMENTS Entery'!G:G,A11,'💳 PAYMENTS Entery'!H:H),0) -> 0 | T11: =H11-S11 -> 5670000 | U11: =IFERROR(MAXIFS('💳 PAYMENTS Entery'!C:C,'💳 PAYMENTS Entery'!G:G,A11),"") | V11: =IFERROR(S11/H11,0) -> 0
A12: 201 | B12: PRJ-001 | C12: B | D12: 2nd | E12: 201 | F12: 522 | G12: 7500 | H12: =G12*F12 -> 3915000 | K12: =H12+I12-J12 -> 3915000 | L12: Booked | M12: =IFERROR(INDEX('👤 Customers'!$A$5:$A$100,MATCH(A12,'👤 Customers'!$K$5:$K$100,0)),"") | N12: =IFERROR(VLOOKUP(M12,'👤 Customers'!A:C,3,0),"") | O12: 15-05-2026 | P12: Monthly-18 | Q12: =IFERROR(COUNTIF('📅 Installments AUTO'!C:C,A12),0) -> 0 | R12: =IFERROR(COUNTIFS('📅 Installments AUTO'!C:C,A12,'📅 Installments AUTO'!N:N,"Paid"),0) -> 0 | S12: =IFERROR(SUMIF('💳 PAYMENTS Entery'!G:G,A12,'💳 PAYMENTS Entery'!H:H),0) -> 0 | T12: =H12-S12 -> 3915000 | U12: =IFERROR(MAXIFS('💳 PAYMENTS Entery'!C:C,'💳 PAYMENTS Entery'!G:G,A12),"") | V12: =IFERROR(S12/H12,0) -> 0
A13: 202 | B13: PRJ-001 | C13: A | D13: 2nd | E13: 202 | F13: 756 | G13: 7500 | H13: =G13*F13 -> 5670000 | K13: =H13+I13-J13 -> 5670000 | L13: Sold | M13: =IFERROR(INDEX('👤 Customers'!$A$5:$A$100,MATCH(A13,'👤 Customers'!$K$5:$K$100,0)),"") -> C-001 | N13: =IFERROR(VLOOKUP(M13,'👤 Customers'!A:C,3,0),"") -> Zulfiqar Ali Sapro | O13: 15-04-2026 | P13: Monthly-18 | Q13: =IFERROR(COUNTIF('📅 Installments AUTO'!C:C,A13),0) -> 0 | R13: =IFERROR(COUNTIFS('📅 Installments AUTO'!C:C,A13,'📅 Installments AUTO'!N:N,"Paid"),0) -> 0 | S13: =IFERROR(SUMIF('💳 PAYMENTS Entery'!G:G,A13,'💳 PAYMENTS Entery'!H:H),0) -> 2430000 | T13: =H13-S13 -> 3240000 | U13: =IFERROR(MAXIFS('💳 PAYMENTS Entery'!C:C,'💳 PAYMENTS Entery'!G:G,A13),"") | V13: =IFERROR(S13/H13,0) -> 0.42857143
A14: 301 | B14: PRJ-001 | C14: B | D14: 3rd | E14: 301 | F14: 522 | G14: 7500 | H14: =G14*F14 -> 3915000 | K14: =H14+I14-J14 -> 3915000 | L14: Available | M14: =IFERROR(INDEX('👤 Customers'!$A$5:$A$100,MATCH(A14,'👤 Customers'!$K$5:$K$100,0)),"") | N14: =IFERROR(VLOOKUP(M14,'👤 Customers'!A:C,3,0),"") | Q14: =IFERROR(COUNTIF('📅 Installments AUTO'!C:C,A14),0) -> 0 | R14: =IFERROR(COUNTIFS('📅 Installments AUTO'!C:C,A14,'📅 Installments AUTO'!N:N,"Paid"),0) -> 0 | S14: =IFERROR(SUMIF('💳 PAYMENTS Entery'!G:G,A14,'💳 PAYMENTS Entery'!H:H),0) -> 0 | T14: =H14-S14 -> 3915000 | U14: =IFERROR(MAXIFS('💳 PAYMENTS Entery'!C:C,'💳 PAYMENTS Entery'!G:G,A14),"") | V14: =IFERROR(S14/H14,0) -> 0
A15: 302 | B15: PRJ-001 | C15: A | D15: 3rd | E15: 302 | F15: 756 | G15: 7500 | H15: =G15*F15 -> 5670000 | K15: =H15+I15-J15 -> 5670000 | L15: Available | M15: =IFERROR(INDEX('👤 Customers'!$A$5:$A$100,MATCH(A15,'👤 Customers'!$K$5:$K$100,0)),"") | N15: =IFERROR(VLOOKUP(M15,'👤 Customers'!A:C,3,0),"") | Q15: =IFERROR(COUNTIF('📅 Installments AUTO'!C:C,A15),0) -> 0 | R15: =IFERROR(COUNTIFS('📅 Installments AUTO'!C:C,A15,'📅 Installments AUTO'!N:N,"Paid"),0) -> 0 | S15: =IFERROR(SUMIF('💳 PAYMENTS Entery'!G:G,A15,'💳 PAYMENTS Entery'!H:H),0) -> 0 | T15: =H15-S15 -> 5670000 | U15: =IFERROR(MAXIFS('💳 PAYMENTS Entery'!C:C,'💳 PAYMENTS Entery'!G:G,A15),"") | V15: =IFERROR(S15/H15,0) -> 0
A16: 401 | B16: PRJ-001 | C16: B | D16: 4th | E16: 401 | F16: 522 | G16: 7500 | H16: =G16*F16 -> 3915000 | K16: =H16+I16-J16 -> 3915000 | L16: Available | M16: =IFERROR(INDEX('👤 Customers'!$A$5:$A$100,MATCH(A16,'👤 Customers'!$K$5:$K$100,0)),"") -> C-004 | N16: =IFERROR(VLOOKUP(M16,'👤 Customers'!A:C,3,0),"") -> aiman | Q16: =IFERROR(COUNTIF('📅 Installments AUTO'!C:C,A16),0) -> 0 | R16: =IFERROR(COUNTIFS('📅 Installments AUTO'!C:C,A16,'📅 Installments AUTO'!N:N,"Paid"),0) -> 0 | S16: =IFERROR(SUMIF('💳 PAYMENTS Entery'!G:G,A16,'💳 PAYMENTS Entery'!H:H),0) -> 0 | T16: =H16-S16 -> 3915000 | U16: =IFERROR(MAXIFS('💳 PAYMENTS Entery'!C:C,'💳 PAYMENTS Entery'!G:G,A16),"") | V16: =IFERROR(S16/H16,0) -> 0
A17: 402 | B17: PRJ-001 | C17: A | D17: 4th | E17: 402 | F17: 756 | G17: 7500 | H17: =G17*F17 -> 5670000 | K17: =H17+I17-J17 -> 5670000 | L17: Available | M17: =IFERROR(INDEX('👤 Customers'!$A$5:$A$100,MATCH(A17,'👤 Customers'!$K$5:$K$100,0)),"") | N17: =IFERROR(VLOOKUP(M17,'👤 Customers'!A:C,3,0),"") | Q17: =IFERROR(COUNTIF('📅 Installments AUTO'!C:C,A17),0) -> 0 | R17: =IFERROR(COUNTIFS('📅 Installments AUTO'!C:C,A17,'📅 Installments AUTO'!N:N,"Paid"),0) -> 0 | S17: =IFERROR(SUMIF('💳 PAYMENTS Entery'!G:G,A17,'💳 PAYMENTS Entery'!H:H),0) -> 0 | T17: =H17-S17 -> 5670000 | U17: =IFERROR(MAXIFS('💳 PAYMENTS Entery'!C:C,'💳 PAYMENTS Entery'!G:G,A17),"") | V17: =IFERROR(S17/H17,0) -> 0
A18: 500 | B18: PRJ-001 | C18: Panthouse | D18: 5th | E18: 500 | F18: 1278 | G18: 7500 | H18: =G18*F18 -> 9585000 | I18: 150000 | J18: 25000 | K18: =H18+I18-J18 -> 9710000 | L18: Available | M18: C-004 | N18: =IFERROR(VLOOKUP(M18,'👤 Customers'!A:C,3,0),"") -> aiman | O18: 15-06-2026 | Q18: =IFERROR(COUNTIF('📅 Installments AUTO'!C:C,A18),0) -> 0 | R18: =IFERROR(COUNTIFS('📅 Installments AUTO'!C:C,A18,'📅 Installments AUTO'!N:N,"Paid"),0) -> 0 | S18: =IFERROR(SUMIF('💳 PAYMENTS Entery'!G:G,A18,'💳 PAYMENTS Entery'!H:H),0) -> 0 | T18: =H18-S18 -> 9585000 | U18: =IFERROR(MAXIFS('💳 PAYMENTS Entery'!C:C,'💳 PAYMENTS Entery'!G:G,A18),"") | V18: =IFERROR(S18/H18,0) -> 0 | W18: 31-12-2027 | X18: 31-12-2027 | Y18: Vip reserve

Sheet 👤 Customers
A1: 👤 CUSTOMER DATABASE — All Buyers
A2: Enter each customer ONCE. All sheets reference Customer ID.
A3: ▌ CUSTOMER REGISTER — Enter once. Never re-enter payment data here.
A4: Customer ID | B4: Registration No | C4: Customer Name | D4: Father/Husband | E4: CNIC | F4: Mobile | G4: WhatsApp | H4: Email | I4: Address | J4: City | K4: Flat ID | L4: Sale Value [AUTO] | M4: Total Paid [AUTO] | N4: Outstanding [AUTO] | O4: % Paid [AUTO] | P4: Status [AUTO] | Q4: Next Due Amt [AUTO] | R4: Next Due Date [AUTO] | S4: Booking Date | T4: Notes
A5: C-001 | B5: AB-Sachal-GH/2024/1/2024 | C5: Zulfiqar Ali Sapro | D5: Sapro Sb | E5: 42101-1234567-1 | F5: 03001234567 | G5: 03001234567 | H5: ali@email.com | I5: House 5 Block A North Nazimabad | J5: Karachi | K5: 202 | L5: =IFERROR(VLOOKUP(K5,'🏘️ Flat Register'!A:H,8,0),0) -> 5670000 | M5: =IFERROR(SUMIF('💳 PAYMENTS Entery'!G:G,K5,'💳 PAYMENTS Entery'!H:H),0) -> 2430000 | N5: =L5-M5 -> 3240000 | O5: =IFERROR(M5/L5,0) -> 0.42857143 | P5: =IF(N5=0,"Cleared",IF(M5=0,"Unpaid","Active")) -> Active | Q5: =IFERROR(MINIFS('📅 Installments AUTO'!I:I,'📅 Installments AUTO'!C:C,K5,'📅 Installments AUTO'!N:N,"Pending"),0) -> 0 | R5: =IFERROR(MINIFS('📅 Installments AUTO'!H:H,'📅 Installments AUTO'!C:C,K5,'📅 Installments AUTO'!N:N,"Pending"),"") | S5: 46157
A6: C-002 | B6: AB-Sachal-GH/2024/2/2024 | C6: Sharjeel | D6: soomro | E6: 42101-1234567-1 | F6: 03001234567 | G6: 03001234567 | H6: ali@email.com | I6: House 5 Block A North Nazimabad | J6: Karachi | K6: 101 | L6: =IFERROR(VLOOKUP(K6,'🏘️ Flat Register'!A:H,8,0),0) -> 3915000 | M6: =IFERROR(SUMIF('💳 PAYMENTS Entery'!G:G,K6,'💳 PAYMENTS Entery'!H:H),0) -> 0 | N6: =L6-M6 -> 3915000 | O6: =IFERROR(M6/L6,0) -> 0 | P6: =IF(N6=0,"Cleared",IF(M6=0,"Unpaid","Active")) -> Unpaid | Q6: =IFERROR(MINIFS('📅 Installments AUTO'!I:I,'📅 Installments AUTO'!C:C,K6,'📅 Installments AUTO'!N:N,"Pending"),0) -> 0 | R6: =IFERROR(MINIFS('📅 Installments AUTO'!H:H,'📅 Installments AUTO'!C:C,K6,'📅 Installments AUTO'!N:N,"Pending"),"") | S6: 46188
A7: C-003 | B7: AB-Sachal-GH/2024/2/2024 | C7: hello | D7: soomro | E7: 42101-1234567-1 | F7: 03001234567 | G7: 03001234567 | H7: ali@email.com | I7: House 5 Block A North Nazimabad | J7: Karachi | K7: 1 | L7: =IFERROR(VLOOKUP(K7,'🏘️ Flat Register'!A:H,8,0),0) -> 3510000 | M7: =IFERROR(SUMIF('💳 PAYMENTS Entery'!G:G,K7,'💳 PAYMENTS Entery'!H:H),0) -> 0 | N7: =L7-M7 -> 3510000 | O7: =IFERROR(M7/L7,0) -> 0 | P7: =IF(N7=0,"Cleared",IF(M7=0,"Unpaid","Active")) -> Unpaid | Q7: =IFERROR(MINIFS('📅 Installments AUTO'!I:I,'📅 Installments AUTO'!C:C,K7,'📅 Installments AUTO'!N:N,"Pending"),0) -> 0 | R7: =IFERROR(MINIFS('📅 Installments AUTO'!H:H,'📅 Installments AUTO'!C:C,K7,'📅 Installments AUTO'!N:N,"Pending"),"") | S7: 46218
A8: C-004 | B8: AB-Sachal-GH/2024/2/2024 | C8: aiman | D8: soomro | E8: 42101-1234567-1 | F8: 03001234567 | G8: 03001234567 | H8: ali@email.com | I8: House 5 Block A North Nazimabad | J8: Karachi | K8: 401 | L8: =IFERROR(VLOOKUP(K8,'🏘️ Flat Register'!A:H,8,0),0) -> 3915000 | M8: =IFERROR(SUMIF('💳 PAYMENTS Entery'!G:G,K8,'💳 PAYMENTS Entery'!H:H),0) -> 0 | N8: =L8-M8 -> 3915000 | O8: =IFERROR(M8/L8,0) -> 0 | P8: =IF(N8=0,"Cleared",IF(M8=0,"Unpaid","Active")) -> Unpaid | Q8: =IFERROR(MINIFS('📅 Installments AUTO'!I:I,'📅 Installments AUTO'!C:C,K8,'📅 Installments AUTO'!N:N,"Pending"),0) -> 0 | R8: =IFERROR(MINIFS('📅 Installments AUTO'!H:H,'📅 Installments AUTO'!C:C,K8,'📅 Installments AUTO'!N:N,"Pending"),"") | S8: 46249

Sheet 📅 Installments AUTO
A1: 📅 Installments AUTO — Generated from Flat Master | DO NOT ENTER DATA HERE
A2: Status | Overdue Days | Late Fee all auto-calculate using TODAY()
A3: 🔒 THIS SHEET IS AUTO-GENERATED. When you set a Flat to Sold in Flat Master, installments appear here automatically. Payments entered in 💳 PAYMENTS mark installments Paid automatically.
A4: Total Inst. | E4: Paid | I4: Overdue | M4: Pending | R4: Overdue Amount
A5: =COUNTA(A11:A49919) -> 12 | E5: =COUNTIF(N11:N49919,"Paid") -> 2 | I5: =COUNTIF(N11:N49919,"Overdue") -> 2 | M5: =COUNTIF(N11:N49919,"Pending") -> 8 | R5: =SUMIF(N11:N49919,"Overdue",K11:K49919) -> 1150000
A7: ▌ INSTALLMENT SCHEDULE — Reads from Flat Master + Payments. All columns auto-calculate.
A8: Inst. ID [AUTO] | B8: Serial [AUTO] | C8: Flat ID [AUTO] | D8: Customer ID [AUTO] | E8: Customer Name [AUTO] | F8: Inst. No. [AUTO] | G8: Type [AUTO] | H8: Due Date [ENTER for each row] | I8: Inst. Amount (PKR) [ENTER] | J8: Paid Amount [AUTO from Payments] | K8: Balance [AUTO] | L8: Pay Date [AUTO] | M8: Days Overdue [AUTO TODAY()] | N8: Status [AUTO] | O8: Receipt No. | P8: Late Fee [AUTO] | Q8: Cumul. Paid [AUTO] | R8: % Done [AUTO] | S8: Notes
A9: ↓ Flat ID, Customer ID, Name auto-fill from Flat Master. Paid Amount auto-reads from Payments sheet. Status, Days Overdue, Late Fee all auto-calculate.
A11: =IF(C11<>"",C11&"-"&TEXT(F11,"00"),"") -> F-202-01 | B11: =IF(C11<>"",ROW()-10,"") -> 1 | C11: F-202 | D11: =IFERROR(VLOOKUP(C11,'🏘️ Flat Register'!A:M,10,0),"") | E11: =IFERROR(VLOOKUP(D11,'👤 Customers'!A:C,2,0),"") | F11: 1 | G11: Advance | H11: 46174 | I11: 2000000 | J11: =IFERROR(SUMIF('💳 PAYMENTS Entery'!L:L,A11,'💳 PAYMENTS Entery'!H:H),0) -> 2000000 | K11: =I11-J11 -> 0 | L11: =IFERROR(MAXIFS('💳 PAYMENTS Entery'!C:C,'💳 PAYMENTS Entery'!G:G,C11),"") | M11: =IF(J11>=I11,0,IF(L11<>"",MAX(0,L11-H11),MAX(0,TODAY()-H11))) -> 0 | N11: =IF(J11>=I11,"Paid",IF(AND(J11>0,J11<I11),"Partial",IF(TODAY()>H11,"Overdue","Pending"))) -> Paid | O11: R-10 | P11: =IF(M11>0,ROUND(M11*I11*0.02/30,0),0) -> 0 | Q11: =IFERROR(SUMIF('💳 PAYMENTS Entery'!G:G,C11,'💳 PAYMENTS Entery'!H:H),0) -> 0 | R11: =IFERROR(Q11/VLOOKUP(C11,'🏘️ Flat Register'!A:H,8,0),0) -> 0
A12: =IF(C12<>"",C12&"-"&TEXT(F12,"00"),"") -> F-202-02 | B12: =IF(C12<>"",ROW()-10,"") -> 2 | C12: F-202 | D12: =IFERROR(VLOOKUP(C12,'🏘️ Flat Register'!A:M,10,0),"") | E12: =IFERROR(VLOOKUP(D12,'👤 Customers'!A:C,2,0),"") | F12: 2 | G12: Monthly | H12: 46113 | I12: 150000 | J12: =IFERROR(SUMIF('💳 PAYMENTS Entery'!L:L,A12,'💳 PAYMENTS Entery'!H:H),0) -> 280000 | K12: =I12-J12 -> -130000 | L12: =IFERROR(MAXIFS('💳 PAYMENTS Entery'!C:C,'💳 PAYMENTS Entery'!G:G,C12),"") | M12: =IF(J12>=I12,0,IF(L12<>"",MAX(0,L12-H12),MAX(0,TODAY()-H12))) -> 0 | N12: =IF(J12>=I12,"Paid",IF(AND(J12>0,J12<I12),"Partial",IF(TODAY()>H12,"Overdue","Pending"))) -> Paid | P12: =IF(M12>0,ROUND(M12*I12*0.02/30,0),0) -> 0 | Q12: =IFERROR(SUMIF('💳 PAYMENTS Entery'!G:G,C12,'💳 PAYMENTS Entery'!H:H),0) -> 0 | R12: =IFERROR(Q12/VLOOKUP(C12,'🏘️ Flat Register'!A:H,8,0),0) -> 0
A13: =IF(C13<>"",C13&"-"&TEXT(F13,"00"),"") -> F-202-03 | B13: =IF(C13<>"",ROW()-10,"") -> 3 | C13: F-202 | D13: =IFERROR(VLOOKUP(C13,'🏘️ Flat Register'!A:M,10,0),"") | E13: =IFERROR(VLOOKUP(D13,'👤 Customers'!A:C,2,0),"") | F13: 3 | G13: Monthly | H13: 46174 | I13: 150000 | J13: =IFERROR(SUMIF('💳 PAYMENTS Entery'!L:L,A13,'💳 PAYMENTS Entery'!H:H),0) -> 0 | K13: =I13-J13 -> 150000 | L13: =IFERROR(MAXIFS('💳 PAYMENTS Entery'!C:C,'💳 PAYMENTS Entery'!G:G,C13),"") | M13: =IF(J13>=I13,0,IF(L13<>"",MAX(0,L13-H13),MAX(0,TODAY()-H13))) -> 53 | N13: =IF(J13>=I13,"Paid",IF(AND(J13>0,J13<I13),"Partial",IF(TODAY()>H13,"Overdue","Pending"))) -> Overdue | P13: =IF(M13>0,ROUND(M13*I13*0.02/30,0),0) -> 5300 | Q13: =IFERROR(SUMIF('💳 PAYMENTS Entery'!G:G,C13,'💳 PAYMENTS Entery'!H:H),0) -> 0 | R13: =IFERROR(Q13/VLOOKUP(C13,'🏘️ Flat Register'!A:H,8,0),0) -> 0
A14: =IF(C14<>"",C14&"-"&TEXT(F14,"00"),"") -> F-202-04 | B14: =IF(C14<>"",ROW()-10,"") -> 4 | C14: F-202 | D14: =IFERROR(VLOOKUP(C14,'🏘️ Flat Register'!A:M,10,0),"") | E14: =IFERROR(VLOOKUP(D14,'👤 Customers'!A:C,2,0),"") | F14: 4 | G14: Quarterly | H14: 46204 | I14: 1000000 | J14: =IFERROR(SUMIF('💳 PAYMENTS Entery'!L:L,A14,'💳 PAYMENTS Entery'!H:H),0) -> 0 | K14: =I14-J14 -> 1000000 | L14: =IFERROR(MAXIFS('💳 PAYMENTS Entery'!C:C,'💳 PAYMENTS Entery'!G:G,C14),"") | M14: =IF(J14>=I14,0,IF(L14<>"",MAX(0,L14-H14),MAX(0,TODAY()-H14))) -> 23 | N14: =IF(J14>=I14,"Paid",IF(AND(J14>0,J14<I14),"Partial",IF(TODAY()>H14,"Overdue","Pending"))) -> Overdue | P14: =IF(M14>0,ROUND(M14*I14*0.02/30,0),0) -> 15333 | Q14: =IFERROR(SUMIF('💳 PAYMENTS Entery'!G:G,C14,'💳 PAYMENTS Entery'!H:H),0) -> 0 | R14: =IFERROR(Q14/VLOOKUP(C14,'🏘️ Flat Register'!A:H,8,0),0) -> 0
A15: =IF(C15<>"",C15&"-"&TEXT(F15,"00"),"") -> F-202-05 | B15: =IF(C15<>"",ROW()-10,"") -> 5 | C15: F-202 | D15: =IFERROR(VLOOKUP(C15,'🏘️ Flat Register'!A:M,10,0),"") | E15: =IFERROR(VLOOKUP(D15,'👤 Customers'!A:C,2,0),"") | F15: 5 | G15: Quarterly | H15: 46235 | I15: 150000 | J15: =IFERROR(SUMIF('💳 PAYMENTS Entery'!L:L,A15,'💳 PAYMENTS Entery'!H:H),0) -> 0 | K15: =I15-J15 -> 150000 | L15: =IFERROR(MAXIFS('💳 PAYMENTS Entery'!C:C,'💳 PAYMENTS Entery'!G:G,C15),"") | M15: =IF(J15>=I15,0,IF(L15<>"",MAX(0,L15-H15),MAX(0,TODAY()-H15))) -> 0 | N15: =IF(J15>=I15,"Paid",IF(AND(J15>0,J15<I15),"Partial",IF(TODAY()>H15,"Overdue","Pending"))) -> Pending | P15: =IF(M15>0,ROUND(M15*I15*0.02/30,0),0) -> 0 | Q15: =IFERROR(SUMIF('💳 PAYMENTS Entery'!G:G,C15,'💳 PAYMENTS Entery'!H:H),0) -> 0 | R15: =IFERROR(Q15/VLOOKUP(C15,'🏘️ Flat Register'!A:H,8,0),0) -> 0
A16: =IF(C16<>"",C16&"-"&TEXT(F16,"00"),"") -> F-202-06 | B16: =IF(C16<>"",ROW()-10,"") -> 6 | C16: F-202 | D16: =IFERROR(VLOOKUP(C16,'🏘️ Flat Register'!A:M,10,0),"") | E16: =IFERROR(VLOOKUP(D16,'👤 Customers'!A:C,2,0),"") | F16: 6 | G16: Quarterly | H16: 46266 | I16: 150000 | J16: =IFERROR(SUMIF('💳 PAYMENTS Entery'!L:L,A16,'💳 PAYMENTS Entery'!H:H),0) -> 0 | K16: =I16-J16 -> 150000 | L16: =IFERROR(MAXIFS('💳 PAYMENTS Entery'!C:C,'💳 PAYMENTS Entery'!G:G,C16),"") | M16: =IF(J16>=I16,0,IF(L16<>"",MAX(0,L16-H16),MAX(0,TODAY()-H16))) -> 0 | N16: =IF(J16>=I16,"Paid",IF(AND(J16>0,J16<I16),"Partial",IF(TODAY()>H16,"Overdue","Pending"))) -> Pending | P16: =IF(M16>0,ROUND(M16*I16*0.02/30,0),0) -> 0 | Q16: =IFERROR(SUMIF('💳 PAYMENTS Entery'!G:G,C16,'💳 PAYMENTS Entery'!H:H),0) -> 0 | R16: =IFERROR(Q16/VLOOKUP(C16,'🏘️ Flat Register'!A:H,8,0),0) -> 0
A17: =IF(C17<>"",C17&"-"&TEXT(F17,"00"),"") -> F-202-07 | B17: =IF(C17<>"",ROW()-10,"") -> 7 | C17: F-202 | D17: =IFERROR(VLOOKUP(C17,'🏘️ Flat Register'!A:M,10,0),"") | E17: =IFERROR(VLOOKUP(D17,'👤 Customers'!A:C,2,0),"") | F17: 7 | G17: Quarterly | H17: 46296 | I17: 1000000 | J17: =IFERROR(SUMIF('💳 PAYMENTS Entery'!L:L,A17,'💳 PAYMENTS Entery'!H:H),0) -> 0 | K17: =I17-J17 -> 1000000 | L17: =IFERROR(MAXIFS('💳 PAYMENTS Entery'!C:C,'💳 PAYMENTS Entery'!G:G,C17),"") | M17: =IF(J17>=I17,0,IF(L17<>"",MAX(0,L17-H17),MAX(0,TODAY()-H17))) -> 0 | N17: =IF(J17>=I17,"Paid",IF(AND(J17>0,J17<I17),"Partial",IF(TODAY()>H17,"Overdue","Pending"))) -> Pending | P17: =IF(M17>0,ROUND(M17*I17*0.02/30,0),0) -> 0 | Q17: =IFERROR(SUMIF('💳 PAYMENTS Entery'!G:G,C17,'💳 PAYMENTS Entery'!H:H),0) -> 0 | R17: =IFERROR(Q17/VLOOKUP(C17,'🏘️ Flat Register'!A:H,8,0),0) -> 0
A18: =IF(C18<>"",C18&"-"&TEXT(F18,"00"),"") -> F-202-08 | B18: =IF(C18<>"",ROW()-10,"") -> 8 | C18: F-202 | D18: =IFERROR(VLOOKUP(C18,'🏘️ Flat Register'!A:M,10,0),"") | E18: =IFERROR(VLOOKUP(D18,'👤 Customers'!A:C,2,0),"") | F18: 8 | G18: Quarterly | H18: 46327 | I18: 150000 | J18: =IFERROR(SUMIF('💳 PAYMENTS Entery'!L:L,A18,'💳 PAYMENTS Entery'!H:H),0) -> 0 | K18: =I18-J18 -> 150000 | L18: =IFERROR(MAXIFS('💳 PAYMENTS Entery'!C:C,'💳 PAYMENTS Entery'!G:G,C18),"") | M18: =IF(J18>=I18,0,IF(L18<>"",MAX(0,L18-H18),MAX(0,TODAY()-H18))) -> 0 | N18: =IF(J18>=I18,"Paid",IF(AND(J18>0,J18<I18),"Partial",IF(TODAY()>H18,"Overdue","Pending"))) -> Pending | P18: =IF(M18>0,ROUND(M18*I18*0.02/30,0),0) -> 0 | Q18: =IFERROR(SUMIF('💳 PAYMENTS Entery'!G:G,C18,'💳 PAYMENTS Entery'!H:H),0) -> 0 | R18: =IFERROR(Q18/VLOOKUP(C18,'🏘️ Flat Register'!A:H,8,0),0) -> 0
A19: =IF(C19<>"",C19&"-"&TEXT(F19,"00"),"") -> F-202-09 | B19: =IF(C19<>"",ROW()-10,"") -> 9 | C19: F-202 | D19: =IFERROR(VLOOKUP(C19,'🏘️ Flat Register'!A:M,10,0),"") | E19: =IFERROR(VLOOKUP(D19,'👤 Customers'!A:C,2,0),"") | F19: 9 | G19: Quarterly | H19: 46357 | I19: 150000 | J19: =IFERROR(SUMIF('💳 PAYMENTS Entery'!L:L,A19,'💳 PAYMENTS Entery'!H:H),0) -> 0 | K19: =I19-J19 -> 150000 | L19: =IFERROR(MAXIFS('💳 PAYMENTS Entery'!C:C,'💳 PAYMENTS Entery'!G:G,C19),"") | M19: =IF(J19>=I19,0,IF(L19<>"",MAX(0,L19-H19),MAX(0,TODAY()-H19))) -> 0 | N19: =IF(J19>=I19,"Paid",IF(AND(J19>0,J19<I19),"Partial",IF(TODAY()>H19,"Overdue","Pending"))) -> Pending | P19: =IF(M19>0,ROUND(M19*I19*0.02/30,0),0) -> 0 | Q19: =IFERROR(SUMIF('💳 PAYMENTS Entery'!G:G,C19,'💳 PAYMENTS Entery'!H:H),0) -> 0 | R19: =IFERROR(Q19/VLOOKUP(C19,'🏘️ Flat Register'!A:H,8,0),0) -> 0
A20: =IF(C20<>"",C20&"-"&TEXT(F20,"00"),"") -> F-202-10 | B20: =IF(C20<>"",ROW()-10,"") -> 10 | C20: F-202 | D20: =IFERROR(VLOOKUP(C20,'🏘️ Flat Register'!A:M,10,0),"") | E20: =IFERROR(VLOOKUP(D20,'👤 Customers'!A:C,2,0),"") | F20: 10 | G20: Quarterly | H20: 46388 | I20: 150000 | J20: =IFERROR(SUMIF('💳 PAYMENTS Entery'!L:L,A20,'💳 PAYMENTS Entery'!H:H),0) -> 0 | K20: =I20-J20 -> 150000 | L20: =IFERROR(MAXIFS('💳 PAYMENTS Entery'!C:C,'💳 PAYMENTS Entery'!G:G,C20),"") | M20: =IF(J20>=I20,0,IF(L20<>"",MAX(0,L20-H20),MAX(0,TODAY()-H20))) -> 0 | N20: =IF(J20>=I20,"Paid",IF(AND(J20>0,J20<I20),"Partial",IF(TODAY()>H20,"Overdue","Pending"))) -> Pending | P20: =IF(M20>0,ROUND(M20*I20*0.02/30,0),0) -> 0 | Q20: =IFERROR(SUMIF('💳 PAYMENTS Entery'!G:G,C20,'💳 PAYMENTS Entery'!H:H),0) -> 0 | R20: =IFERROR(Q20/VLOOKUP(C20,'🏘️ Flat Register'!A:H,8,0),0) -> 0
A21: =IF(C21<>"",C21&"-"&TEXT(F21,"00"),"") -> F-202-11 | B21: =IF(C21<>"",ROW()-10,"") -> 11 | C21: F-202 | D21: =IFERROR(VLOOKUP(C21,'🏘️ Flat Register'!A:M,10,0),"") | E21: =IFERROR(VLOOKUP(D21,'👤 Customers'!A:C,2,0),"") | F21: 11 | G21: Quarterly | H21: 46419 | I21: 150000 | J21: =IFERROR(SUMIF('💳 PAYMENTS Entery'!L:L,A21,'💳 PAYMENTS Entery'!H:H),0) -> 0 | K21: =I21-J21 -> 150000 | L21: =IFERROR(MAXIFS('💳 PAYMENTS Entery'!C:C,'💳 PAYMENTS Entery'!G:G,C21),"") | M21: =IF(J21>=I21,0,IF(L21<>"",MAX(0,L21-H21),MAX(0,TODAY()-H21))) -> 0 | N21: =IF(J21>=I21,"Paid",IF(AND(J21>0,J21<I21),"Partial",IF(TODAY()>H21,"Overdue","Pending"))) -> Pending | P21: =IF(M21>0,ROUND(M21*I21*0.02/30,0),0) -> 0 | Q21: =IFERROR(SUMIF('💳 PAYMENTS Entery'!G:G,C21,'💳 PAYMENTS Entery'!H:H),0) -> 0 | R21: =IFERROR(Q21/VLOOKUP(C21,'🏘️ Flat Register'!A:H,8,0),0) -> 0
A22: =IF(C22<>"",C22&"-"&TEXT(F22,"00"),"") -> F-202-12 | B22: =IF(C22<>"",ROW()-10,"") -> 12 | C22: F-202 | D22: =IFERROR(VLOOKUP(C22,'🏘️ Flat Register'!A:M,10,0),"") | E22: =IFERROR(VLOOKUP(D22,'👤 Customers'!A:C,2,0),"") | F22: 12 | G22: Quarterly | H22: 46447 | I22: 150000 | J22: =IFERROR(SUMIF('💳 PAYMENTS Entery'!L:L,A22,'💳 PAYMENTS Entery'!H:H),0) -> 0 | K22: =I22-J22 -> 150000 | L22: =IFERROR(MAXIFS('💳 PAYMENTS Entery'!C:C,'💳 PAYMENTS Entery'!G:G,C22),"") | M22: =IF(J22>=I22,0,IF(L22<>"",MAX(0,L22-H22),MAX(0,TODAY()-H22))) -> 0 | N22: =IF(J22>=I22,"Paid",IF(AND(J22>0,J22<I22),"Partial",IF(TODAY()>H22,"Overdue","Pending"))) -> Pending | P22: =IF(M22>0,ROUND(M22*I22*0.02/30,0),0) -> 0 | Q22: =IFERROR(SUMIF('💳 PAYMENTS Entery'!G:G,C22,'💳 PAYMENTS Entery'!H:H),0) -> 0 | R22: =IFERROR(Q22/VLOOKUP(C22,'🏘️ Flat Register'!A:H,8,0),0) -> 0

Sheet 📋 Booking Register
A1: 📋 BOOKING REGISTER — One Entry Per Flat
A2: Enter booking once. Payment schedule auto-generates from plan template.
A3: ▌ BOOKING LOG
A4: Booking ID | B4: Booking Date | C4: Flat No | D4: Customer ID | E4: Customer Name [AUTO] | F4: Project [AUTO] | G4: Block [AUTO] | H4: Floor [AUTO] | I4: Size sqft [AUTO] | J4: Total Price [AUTO] | K4: Extra Charges | L4: Discount | M4: Net Price [AUTO] | N4: Payment Plan | O4: Down Payment | P4: No. of Inst. | Q4: Inst. Amount [AUTO] | R4: Inst. Freq. | S4: Completion Date | T4: Booking Status | U4: Notes
A5: =IF(C5<>"","BK-"&TEXT(C5,"000"),"") -> BK-302 | B5: 44927 | C5: 302 | D5: C-001 | E5: =IFERROR(INDEX('👤 Customers'!C5:C5231,MATCH(D5,'👤 Customers'!A5:A5233)),"") -> Zulfiqar Ali Sapro | F5: =IFERROR(INDEX('🏘️ Flat Register'!B8:B18,MATCH(C5,'🏘️ Flat Register'!E8:E18,0)),"") -> PRJ-001 | G5: =IFERROR(INDEX('🏘️ Flat Register'!C8:C18,MATCH(C5,'🏘️ Flat Register'!E8:E18,0)),"") -> A | H5: =IFERROR(INDEX('🏘️ Flat Register'!D8:D18,MATCH(C5,'🏘️ Flat Register'!E8:E18,0)),"") -> 3rd | I5: =IFERROR(INDEX('🏘️ Flat Register'!F8:F18,MATCH(C5,'🏘️ Flat Register'!E8:E18,0)),"") -> 756 | J5: =IFERROR(INDEX('🏘️ Flat Register'!H8:H18,MATCH(C5,'🏘️ Flat Register'!E8:E18,0)),0) -> 5670000 | K5: 0 | L5: 0 | M5: =J5+K5-L5 -> 5670000 | N5: Monthly-11 | O5: 500000 | P5: 11 | Q5: =IFERROR((M5-N5)/P5,0) -> 0 | R5: Monthly | S5: 31-Dec-2025 | T5: Active
A6: =IF(C6<>"","BK-"&TEXT(C6,"000"),"") -> BK-401 | B6: 44927 | C6: 401 | D6: C-002 | E6: =IFERROR(INDEX('👤 Customers'!C6:C5232,MATCH(D6,'👤 Customers'!A6:A5234)),"") -> Sharjeel | F6: =IFERROR(INDEX('🏘️ Flat Register'!B9:B19,MATCH(C6,'🏘️ Flat Register'!E9:E19,0)),"") -> PRJ-001 | G6: =IFERROR(INDEX('🏘️ Flat Register'!C9:C19,MATCH(C6,'🏘️ Flat Register'!E9:E19,0)),"") -> B | H6: =IFERROR(INDEX('🏘️ Flat Register'!D9:D19,MATCH(C6,'🏘️ Flat Register'!E9:E19,0)),"") -> 4th | I6: =IFERROR(INDEX('🏘️ Flat Register'!F9:F19,MATCH(C6,'🏘️ Flat Register'!E9:E19,0)),"") -> 522 | J6: =IFERROR(INDEX('🏘️ Flat Register'!H9:H19,MATCH(C6,'🏘️ Flat Register'!E9:E19,0)),0) -> 3915000 | K6: 0 | L6: 0 | M6: =J6+K6-L6 -> 3915000 | N6: Monthly-11 | O6: 500000 | P6: 11 | Q6: =IFERROR((M6-N6)/P6,0) -> 0 | R6: Monthly | S6: 31-Dec-2025 | T6: Active

Sheet 📄 Customer Statement
A1: 📄 CUSTOMER ACCOUNT STATEMENT - EMAAN HOLDINGS
A2: Type Flat No in cell B4 (yellow). Full statement auto-generates instantly.
A3: Enter Flat No →
A4: Flat No: | B4: 500
A6: Gohar Enclave Maroara
A7: Account Statement
A9: Personal Information:
A10: Registration No: | C10: =IFERROR(INDEX('👤 Customers'!B:B,MATCH(IFERROR(INDEX('🏘️ Flat Register'!M:M,MATCH($B$4,'🏘️ Flat Register'!E:E,0)),""),'👤 Customers'!A:A,0)),"") -> AB-Sachal-GH/2024/2/2024 | I10: Cell No | K10: =IFERROR(INDEX('👤 Customers'!F:F,MATCH(IFERROR(INDEX('🏘️ Flat Register'!M:M,MATCH($B$4,'🏘️ Flat Register'!E:E,0)),""),'👤 Customers'!A:A,0)),"") -> 03001234567
A11: Name: | C11: =IFERROR(INDEX('👤 Customers'!C:C,MATCH(IFERROR(INDEX('🏘️ Flat Register'!M:M,MATCH($B$4,'🏘️ Flat Register'!E:E,0)),""),'👤 Customers'!A:A,0)),"") -> aiman | I11: PTCL No. | K11: =IFERROR(INDEX('👤 Customers'!G:G,MATCH(IFERROR(INDEX('🏘️ Flat Register'!M:M,MATCH($B$4,'🏘️ Flat Register'!E:E,0)),""),'👤 Customers'!A:A,0)),"") -> 03001234567
A12: Father Name: | C12: =IFERROR(INDEX('👤 Customers'!D:D,MATCH(IFERROR(INDEX('🏘️ Flat Register'!M:M,MATCH($B$4,'🏘️ Flat Register'!E:E,0)),""),'👤 Customers'!A:A,0)),"") -> soomro | I12: Email: | K12: =IFERROR(INDEX('👤 Customers'!H:H,MATCH(IFERROR(INDEX('🏘️ Flat Register'!M:M,MATCH($B$4,'🏘️ Flat Register'!E:E,0)),""),'👤 Customers'!A:A,0)),"") -> ali@email.com
A13: Cnic | C13: =IFERROR(INDEX('👤 Customers'!E:E,MATCH(IFERROR(INDEX('🏘️ Flat Register'!M:M,MATCH($B$4,'🏘️ Flat Register'!E:E,0)),""),'👤 Customers'!A:A,0)),"") -> 42101-1234567-1
A14: Address | C14: =IFERROR(INDEX('👤 Customers'!I:I,MATCH(IFERROR(INDEX('🏘️ Flat Register'!M:M,MATCH($B$4,'🏘️ Flat Register'!E:E,0)),""),'👤 Customers'!A:A,0)),"") -> House 5 Block A North Nazimabad
A15: Flat/Shop Information:
A16: Project Name | C16: =IFERROR(INDEX('🏗️ Projects'!B:B,MATCH(IFERROR(INDEX('🏘️ Flat Register'!B:B,MATCH($B$4,'🏘️ Flat Register'!E:E,0)),""),'🏗️ Projects'!A:A,0)),"") -> Marora Residency | I16: Start Date | L16: =IFERROR(INDEX('🏗️ Projects'!E:E,MATCH(IFERROR(INDEX('🏘️ Flat Register'!B:B,MATCH($B$4,'🏘️ Flat Register'!E:E,0)),""),'🏗️ Projects'!A:A,0)),"") -> 15-01-2026
A17: Block | C17: =IFERROR(INDEX('🏘️ Flat Register'!C:C,MATCH($B$4,'🏘️ Flat Register'!E:E,0)),"") -> Panthouse | I17: Booking Date | L17: =IFERROR(INDEX('🏘️ Flat Register'!O:O,MATCH($B$4,'🏘️ Flat Register'!E:E,0)),"") -> 15-06-2026
A18: Location | C18: D-91, Block D. Sachal Goth | I18: Completion Date | L18: =IFERROR(INDEX('🏘️ Flat Register'!W:W,MATCH($B$4,'🏘️ Flat Register'!E:E,0)),"") -> 31-12-2027
A19: Flat/Shop No | C19: =$B$4 -> 500 | I19: Possession Date | L19: =IFERROR(INDEX('🏘️ Flat Register'!X:X,MATCH($B$4,'🏘️ Flat Register'!E:E,0)),"") -> 31-12-2027
A20: Type | C20: =IFERROR(INDEX('🏘️ Flat Register'!C:C,MATCH($B$4,'🏘️ Flat Register'!E:E,0)),"") -> Panthouse
A21: Size | C21: =IFERROR(INDEX('🏘️ Flat Register'!F:F,MATCH($B$4,'🏘️ Flat Register'!E:E,0)),"")&" Sqyard" -> 1278 Sqyard
A22: Floor | C22: =IFERROR(INDEX('🏘️ Flat Register'!D:D,MATCH($B$4,'🏘️ Flat Register'!E:E,0)),"") -> 5th
A23: Payment Summary:
A24: Total Amt | B24: Extra Charges | C24: Discount | E24: Net Amt | F24: Rec Amt | G24: PDC Amt | J24: Waive Amt | K24: O/S Amt | L24: Over Due Amt
A25: =IFERROR(INDEX('🏘️ Flat Register'!H:H,MATCH($B$4,'🏘️ Flat Register'!E:E,0)),0) -> 9585000 | B25: =IFERROR(INDEX('🏘️ Flat Register'!I:I,MATCH($B$4,'🏘️ Flat Register'!E:E,0)),0) -> 150000 | C25: =IFERROR(INDEX('🏘️ Flat Register'!J:J,MATCH($B$4,'🏘️ Flat Register'!E:E,0)),0) -> 25000 | E25: =IFERROR(INDEX('🏘️ Flat Register'!K:K,MATCH($B$4,'🏘️ Flat Register'!E:E,0)),0) -> 9710000 | F25: =IFERROR(SUMIF('💳 PAYMENTS Entery'!G:G,$B$4,'💳 PAYMENTS Entery'!H:H),0) -> 0 | G25: 0 | J25: 0 | K25: =IFERROR(INDEX('🏘️ Flat Register'!K:K,MATCH($B$4,'🏘️ Flat Register'!A:A,0)),0)-IFERROR(SUMIF('💳 PAYMENTS Entery'!G:G,$B$4,'💳 PAYMENTS Entery'!H:H),0) -> 9710000 | L25: =IFERROR(SUMIFS('💳 PAYMENTS Entery'!H:H,'💳 PAYMENTS Entery'!G:G,$B$4,'💳 PAYMENTS Entery'!C:C,"<"&TODAY()),0) -> 0
A27: Payment Types | B27: Inst # | C27: Due Date | D27: Due Amt | E27: Rec Amt | F27: O.S Amt | G27: Charges | I27: Paid On | J27: Mode | K27: Cheque # | L27: Receipt # | M27: Receipt Amt
A28: Cost of form
A29: Membership Fee | C29: =IFERROR(SUMIF('[2]💳 Payment Entry'!G:G,"Membership Fee",'[2]💳 Payment Entry'!H:H),0) -> 500000 | D29: =IFERROR(SUMIF('[2]💳 Payment Entry'!G:G,"Membership Fee",'[2]💳 Payment Entry'!H:H),0) -> 500000 | E29: 0 | G29: 28-Oct-2025 | I29: 45787 | J29: cash | L29: 350000
A30: Confirmation | C30: =IFERROR(SUMIF('[2]💳 Payment Entry'!G:G,"Confirmation",'[2]💳 Payment Entry'!H:H),0) -> 500000 | D30: =IFERROR(SUMIF('[2]💳 Payment Entry'!G:G,"Confirmation",'[2]💳 Payment Entry'!H:H),0) -> 500000 | E30: 0 | G30: 21-Dec-2025 | I30: Online | L30: 200,000
A31: Allocation | C31: =IFERROR(SUMIF('[2]💳 Payment Entry'!G:G,"Allocation",'[2]💳 Payment Entry'!H:H),0) -> 500000 | D31: =IFERROR(SUMIF('[2]💳 Payment Entry'!G:G,"Allocation",'[2]💳 Payment Entry'!H:H),0) -> 500000 | E31: 0 | G31: 2-Feb-2026 | I31: Online | L31: 200,000
A32: Start of work | D32: 0 | G32: 27-Feb-2026 | I32: Cash | L32: 200,000
A33: Installment | B33: 1 | C33: 10-May-2025 | D33: 350000 | E33: =IFERROR(SUMIFS('[2]💳 Payment Entry'!H:H,'[2]💳 Payment Entry'!D:D,$B$4,'[2]💳 Payment Entry'!G:G,"Installment 1"),0) -> 0 | F33: 0 | I33: 29-Apr-2026 | J33: Online | M33: 150,000
A34: Installment | B34: 2 | C34: 11-May-2025 | D34: 350000 | E34: =IFERROR(SUMIFS('[2]💳 Payment Entry'!H:H,'[2]💳 Payment Entry'!D:D,$B$4,'[2]💳 Payment Entry'!G:G,"Installment 2"),0) -> 0 | F34: 0 | I34: 25-May-2025 | J34: Online | M34: 350,000
A35: Installment | B35: 3 | C35: 12-May-2025 | D35: 350000 | E35: =IFERROR(SUMIFS('[2]💳 Payment Entry'!H:H,'[2]💳 Payment Entry'!D:D,$B$4,'[2]💳 Payment Entry'!G:G,"Installment 3"),0) -> 0 | F35: 0 | I35: 16-Jun-2026 | J35: Online | M35: 800,000
A36: Installment | B36: 4 | C36: 1-Jan-2026 | D36: 350000 | E36: =IFERROR(SUMIFS('[2]💳 Payment Entry'!H:H,'[2]💳 Payment Entry'!D:D,$B$4,'[2]💳 Payment Entry'!G:G,"Installment 4"),0) -> 0 | F36: 0
A37: Installment | B37: 5 | C37: 2-Jan-2026 | D37: 350000 | E37: 0 | F37: =D38-E38 -> 300000
A38: Installment | B38: 6 | C38: 3-Mar-2026 | D38: 350000 | E38: 50000 | F38: =D39-E39 -> 350000 | G38: 300000
A39: Installment | B39: 7 | C39: 4-Mar-2026 | D39: 350000 | E39: 0 | F39: =D40-E40 -> 350000
A40: Installment | B40: 8 | C40: 5-May-2026 | D40: 350000 | E40: 0 | F40: =D41-E41 -> 350000 | G40: 350000
A41: Installment | B41: 9 | C41: 6-May-2026 | D41: 350000 | E41: 0 | F41: =D42-E42 -> 350000 | G41: 350000
A42: Installment | B42: 10 | C42: 7-May-2026 | D42: 350000 | E42: 0 | F42: =D43-E43 -> 800000 | G42: 350000
A43: Possession | B43: 11 | C43: 30-Jul-2026 | D43: 800000 | E43: 0 | F43: =D44-E44 -> 0 | G43: 800000
A44: False ceiling | C44: 35000 | D44: 0 | E44: =D45-E45 -> 0 | F44: 35000
A45: Total | D45: =IFERROR(INDEX('[2]🏘️ Flat Register'!H:H,MATCH($B$4,'[2]🏘️ Flat Register'!A:A,0)),0) -> 0 | E45: =IFERROR(SUMIF('[2]💳 Payment Entry'!D:D,$B$4,'[2]💳 Payment Entry'!H:H),0) -> 0 | F45: =IFERROR(INDEX('[2]🏘️ Flat Register'!K:K,MATCH($B$4,'[2]🏘️ Flat Register'!A:A,0)),0)-IFERROR(SUMIF('[2]💳 Payment Entry'!D:D,$B$4,'[2]💳 Payment Entry'!H:H),0) -> 0 | M45: 3,300,000
K47: Print Date | M47: =NOW() -> 46227.926

Sheet 📒 Payment Register
A1: 📒 PAYMENT REGISTER — Auto from Payment Entry
A2: All data reads from 💳 Payment Entry. No manual entry here.
A3: 🔒 AUTO SHEET — Reads 💳 Payment Entry. Filter by Flat No or Customer to see ledger.
A4: Total Receipts | F4: Distinct Flats | K4: Online/Bank | P4: Cash
A5: =SUM('💳 PAYMENTS Entery'!H11:H30) -> 2580000 | F5: =SUMPRODUCT(1/COUNTIF('💳 PAYMENTS Entery'!D11:D45,'💳 PAYMENTS Entery'!D11:D41)) -> #DIV/0! | K5: =IFERROR(SUMIF(H9:H49967,"Bank Transfer",G9:G49967)+SUMIF(H9:H49967,"Cheque",G9:G49967)+SUMIF(H9:H49967,"Online Transfer",G9:G49967)+SUMIF(H9:H49967,"Pay Order",G9:G49967),0) -> 685000 | P5: =IFERROR(SUMIF(H9:H49967,"Cash",G9:G49967),0) -> 1895000
A7: ▌ PAYMENT LEDGER (mirrors Payment Entry)
A8: Receipt No | B8: Date | C8: Flat No | D8: Customer ID | E8: Customer Name | F8: Payment Type | G8: Amount (PKR) | H8: Mode | I8: Cheque/TT | J8: Received By | K8: Notes
A9: ='💳 PAYMENTS Entery'!A11 -> RCP-001 | B9: ='💳 PAYMENTS Entery'!C11 -> 46157 | C9: ='💳 PAYMENTS Entery'!G11 -> 202 | D9: ='💳 PAYMENTS Entery'!D11 -> C-001 | E9: ='💳 PAYMENTS Entery'!E11 -> Zulfiqar Ali Sapro | F9: ='💳 PAYMENTS Entery'!F11 -> Confirmation | G9: ='💳 PAYMENTS Entery'!H11 -> 385000 | H9: ='💳 PAYMENTS Entery'!I11 -> Bank Transfer | I9: ='💳 PAYMENTS Entery'!K11 -> TT-2001 | J9: ='💳 PAYMENTS Entery'!M11 -> Sharjeel | K9: ='💳 PAYMENTS Entery'!N11 -> Installment 1 payment
A10: ='💳 PAYMENTS Entery'!A12 -> R-002 | B10: ='💳 PAYMENTS Entery'!C12 -> 46188 | C10: ='💳 PAYMENTS Entery'!G12 -> 202 | D10: ='💳 PAYMENTS Entery'!D12 -> C-001 | E10: ='💳 PAYMENTS Entery'!E12 -> Zulfiqar Ali Sapro | F10: ='💳 PAYMENTS Entery'!F12 -> Allocation | G10: ='💳 PAYMENTS Entery'!H12 -> 1190000 | H10: ='💳 PAYMENTS Entery'!I12 -> Cash | I10: ='💳 PAYMENTS Entery'!K12 -> 0 | J10: ='💳 PAYMENTS Entery'!M12 -> Sharjeel | K10: ='💳 PAYMENTS Entery'!N12 -> Installment 1 payment
A11: ='💳 PAYMENTS Entery'!A13 -> R-003 | B11: ='💳 PAYMENTS Entery'!C13 -> 46218 | C11: ='💳 PAYMENTS Entery'!G13 -> 202 | D11: ='💳 PAYMENTS Entery'!D13 -> C-001 | E11: ='💳 PAYMENTS Entery'!E13 -> Zulfiqar Ali Sapro | F11: ='💳 PAYMENTS Entery'!F13 -> Installment | G11: ='💳 PAYMENTS Entery'!H13 -> 150000 | H11: ='💳 PAYMENTS Entery'!I13 -> Cash | I11: ='💳 PAYMENTS Entery'!K13 -> 0 | J11: ='💳 PAYMENTS Entery'!M13 -> Sharjeel | K11: ='💳 PAYMENTS Entery'!N13 -> Installment 1 payment
A12: ='💳 PAYMENTS Entery'!A14 -> R-004 | B12: ='💳 PAYMENTS Entery'!C14 -> 46249 | C12: ='💳 PAYMENTS Entery'!G14 -> 202 | D12: ='💳 PAYMENTS Entery'!D14 -> C-001 | E12: ='💳 PAYMENTS Entery'!E14 -> Zulfiqar Ali Sapro | F12: ='💳 PAYMENTS Entery'!F14 -> Installment | G12: ='💳 PAYMENTS Entery'!H14 -> 275000 | H12: ='💳 PAYMENTS Entery'!I14 -> Cash | I12: ='💳 PAYMENTS Entery'!K14 -> 0 | J12: ='💳 PAYMENTS Entery'!M14 -> Sharjeel | K12: ='💳 PAYMENTS Entery'!N14 -> Installment 1 payment
A13: ='💳 PAYMENTS Entery'!A15 -> R-005 | B13: ='💳 PAYMENTS Entery'!C15 -> 46280 | C13: ='💳 PAYMENTS Entery'!G15 -> 202 | D13: ='💳 PAYMENTS Entery'!D15 -> C-001 | E13: ='💳 PAYMENTS Entery'!E15 -> Zulfiqar Ali Sapro | F13: ='💳 PAYMENTS Entery'!F15 -> Installment | G13: ='💳 PAYMENTS Entery'!H15 -> 280000 | H13: ='💳 PAYMENTS Entery'!I15 -> Cash | I13: ='💳 PAYMENTS Entery'!K15 -> 0 | J13: ='💳 PAYMENTS Entery'!M15 -> Sharjeel | K13: ='💳 PAYMENTS Entery'!N15 -> Installment 1 payment, same recp
A14: ='💳 PAYMENTS Entery'!A16 -> R-006 | B14: ='💳 PAYMENTS Entery'!C16 -> 0 | C14: ='💳 PAYMENTS Entery'!G16 -> 202 | D14: ='💳 PAYMENTS Entery'!D16 -> C-001 | E14: ='💳 PAYMENTS Entery'!E16 -> Zulfiqar Ali Sapro | F14: ='💳 PAYMENTS Entery'!F16 -> Installment | G14: ='💳 PAYMENTS Entery'!H16 -> 150000 | H14: ='💳 PAYMENTS Entery'!I16 -> Online Transfer | I14: ='💳 PAYMENTS Entery'!K16 -> 4525 | J14: ='💳 PAYMENTS Entery'!M16 -> 0 | K14: ='💳 PAYMENTS Entery'!N16 -> 0
A15: ='💳 PAYMENTS Entery'!A17 | B15: ='💳 PAYMENTS Entery'!C17 -> 0 | C15: ='💳 PAYMENTS Entery'!G17 | D15: ='💳 PAYMENTS Entery'!D17 -> 0 | E15: ='💳 PAYMENTS Entery'!E17 | F15: ='💳 PAYMENTS Entery'!F17 -> Membership Fee | G15: ='💳 PAYMENTS Entery'!H17 -> 150000 | H15: ='💳 PAYMENTS Entery'!I17 -> Online Transfer | I15: ='💳 PAYMENTS Entery'!K17 -> 0 | J15: ='💳 PAYMENTS Entery'!M17 -> 0 | K15: ='💳 PAYMENTS Entery'!N17 -> 0

Sheet 📋 Receivables AUTO
A1: 📋 Receivables AUTO — Reads from Payments | DO NOT ENTER DATA HERE
A2: 4-bucket aging auto-calculated | Priority flags auto | All from single payment entry
A3: 🔒 AUTO SHEET — All data reads from 💳 PAYMENTS sheet. No entry needed here.
A4: Outstanding | E4: 0-30 Days | I4: 31-60 Days | M4: >60 Days | Q4: Collection %
A5: =SUM(F8:F5000) -> 7155000 | E5: =SUM(G8:G5000) -> 0 | I5: =SUM(H8:H5000) -> 0 | M5: =SUM(I8:I5000)+SUM(J8:J5000) -> 0 | Q5: =IFERROR(SUM('💳 PAYMENTS Entery'!H:H)/SUMIF('🏘️ Flat Register'!L:L,"Sold",'🏘️ Flat Register'!H:H),0) -> 0.45502646
A7: ▌ RECEIVABLES AGING — Auto from Flat Master + Payments
A8: Flat ID | B8: Customer ID | C8: Customer Name | D8: Sale Value (PKR) | E8: Paid (PKR) | F8: Outstanding (PKR) | G8: 0-30 Days (PKR) | H8: 31-60 Days (PKR) | I8: 61-90 Days (PKR) | J8: >90 Days (PKR) | K8: % Collected | L8: Next Due Date | M8: Next Amt (PKR) | N8: Priority | O8: Notes
A9: 101 | B9: C-001 | C9: =IFERROR(VLOOKUP(B9,'👤 Customers'!A:C,3,0),"") -> Zulfiqar Ali Sapro | D9: =IFERROR(VLOOKUP(A9,'🏘️ Flat Register'!A:H,8,0),0) -> 3915000 | E9: =IFERROR(SUMIF('💳 PAYMENTS Entery'!G:G,A9,'💳 PAYMENTS Entery'!H:H),0) -> 0 | F9: =D9-E9 -> 3915000 | G9: =IFERROR(SUMIFS('📅 Installments AUTO'!K:K,'📅 Installments AUTO'!C:C,A9,'📅 Installments AUTO'!M:M,">0",'📅 Installments AUTO'!M:M,"<=30"),0) -> 0 | H9: =IFERROR(SUMIFS('📅 Installments AUTO'!K:K,'📅 Installments AUTO'!C:C,A9,'📅 Installments AUTO'!M:M,">30",'📅 Installments AUTO'!M:M,"<=60"),0) -> 0 | I9: =IFERROR(SUMIFS('📅 Installments AUTO'!K:K,'📅 Installments AUTO'!C:C,A9,'📅 Installments AUTO'!M:M,">60",'📅 Installments AUTO'!M:M,"<=90"),0) -> 0 | J9: =IFERROR(SUMIFS('📅 Installments AUTO'!K:K,'📅 Installments AUTO'!C:C,A9,'📅 Installments AUTO'!M:M,">90"),0) -> 0 | K9: =IFERROR(E9/D9,0) -> 0 | L9: =IFERROR(MINIFS('📅 Installments AUTO'!H:H,'📅 Installments AUTO'!C:C,A9,'📅 Installments AUTO'!N:N,"Pending"),"") | M9: =IFERROR(MINIFS('📅 Installments AUTO'!I:I,'📅 Installments AUTO'!C:C,A9,'📅 Installments AUTO'!N:N,"Pending"),0) -> 0 | N9: =IF(F9>5000000,"HIGH",IF(F9>1000000,"MED","LOW")) -> MED
A10: 202 | B10: C-002 | C10: =IFERROR(VLOOKUP(B10,'👤 Customers'!A:C,3,0),"") -> Sharjeel | D10: =IFERROR(VLOOKUP(A10,'🏘️ Flat Register'!A:H,8,0),0) -> 5670000 | E10: =IFERROR(SUMIF('💳 PAYMENTS Entery'!G:G,A10,'💳 PAYMENTS Entery'!H:H),0) -> 2430000 | F10: =D10-E10 -> 3240000 | G10: =IFERROR(SUMIFS('📅 Installments AUTO'!K:K,'📅 Installments AUTO'!C:C,A10,'📅 Installments AUTO'!M:M,">0",'📅 Installments AUTO'!M:M,"<=30"),0) -> 0 | H10: =IFERROR(SUMIFS('📅 Installments AUTO'!K:K,'📅 Installments AUTO'!C:C,A10,'📅 Installments AUTO'!M:M,">30",'📅 Installments AUTO'!M:M,"<=60"),0) -> 0 | I10: =IFERROR(SUMIFS('📅 Installments AUTO'!K:K,'📅 Installments AUTO'!C:C,A10,'📅 Installments AUTO'!M:M,">60",'📅 Installments AUTO'!M:M,"<=90"),0) -> 0 | J10: =IFERROR(SUMIFS('📅 Installments AUTO'!K:K,'📅 Installments AUTO'!C:C,A10,'📅 Installments AUTO'!M:M,">90"),0) -> 0 | K10: =IFERROR(E10/D10,0) -> 0.42857143 | L10: =IFERROR(MINIFS('📅 Installments AUTO'!H:H,'📅 Installments AUTO'!C:C,A10,'📅 Installments AUTO'!N:N,"Pending"),"") | M10: =IFERROR(MINIFS('📅 Installments AUTO'!I:I,'📅 Installments AUTO'!C:C,A10,'📅 Installments AUTO'!N:N,"Pending"),0) -> 0 | N10: =IF(F10>5000000,"HIGH",IF(F10>1000000,"MED","LOW")) -> MED

Sheet 🏪 Vendors
A1: 🏪 VENDOR MASTER — Enter once. Payable auto-calculates from Purchases.
A2: N
A3: Vendor ID | B3: Vendor Name | C3: Category | D3: Contact | E3: Phone | F3: Email | G3: NTN | H3: Credit Days | I3: Total POs [AUTO] | J3: Paid [AUTO] | K3: Balance [AUTO] | L3: Status
A4: V-001 | B4: Mansoor Ali | C4: cement and Blocks | D4: Raheem Khan | E4: 03111234567 | F4: abc@cement.pk | G4: 1234567-8 | H4: 90 | I4: =IFERROR(SUMIF('📦 PURCHASES ← Enter Here'!D:D,A4,'📦 PURCHASES ← Enter Here'!K:K),0) -> 0 | J4: =IFERROR(SUMIF('🧾 EXPENSES ← Enter Here'!G:G,B4,'🧾 EXPENSES ← Enter Here'!J:J),0) -> 0 | K4: =I4-J4 -> 0 | L4: Active
A5: V-002 | B5: Saeed khan | C5: Steel | D5: Saleem Baig | E5: 03217654321 | F5: steel@world.pk | G5: 8765432-1 | H5: 60 | I5: =IFERROR(SUMIF('📦 PURCHASES ← Enter Here'!D:D,A5,'📦 PURCHASES ← Enter Here'!K:K),0) -> 0 | J5: =IFERROR(SUMIF('🧾 EXPENSES ← Enter Here'!G:G,B5,'🧾 EXPENSES ← Enter Here'!J:J),0) -> 0 | K5: =I5-J5 -> 0 | L5: Active
A6: V-003 | B6: Gul Zaib khan | C6: Hardware | D6: Asif Raza | E6: 03001112222 | F6: fast@log.pk | G6: 5678901-2 | H6: 35 | I6: =IFERROR(SUMIF('📦 PURCHASES ← Enter Here'!D:D,A6,'📦 PURCHASES ← Enter Here'!K:K),0) -> 0 | J6: =IFERROR(SUMIF('🧾 EXPENSES ← Enter Here'!G:G,B6,'🧾 EXPENSES ← Enter Here'!J:J),0) -> 0 | K6: =I6-J6 -> 0 | L6: Active
A7: V-004 | B7: Dawood Jan | C7: Raay / Bajri | D7: Asif Raza | E7: 03001112222 | F7: fast@log.pk | G7: 5678901-2 | H7: 120 | I7: =IFERROR(SUMIF('📦 PURCHASES ← Enter Here'!D:D,A7,'📦 PURCHASES ← Enter Here'!K:K),0) -> 0 | J7: =IFERROR(SUMIF('🧾 EXPENSES ← Enter Here'!G:G,B7,'🧾 EXPENSES ← Enter Here'!J:J),0) -> 0 | K7: =I7-J7 -> 0 | L7: Active

Sheet 👷 Contractors
A1: 👷 CONTRACTOR MASTER — Bills auto from Site Log. Retention auto-deducted.
A2: N
A3: Contractor ID | B3: Name | C3: Specialty | D3: Contact | E3: Contract (PKR) | F3: Bills [AUTO] | G3: Retention [AUTO] | H3: Net Payable [AUTO] | I3: Paid [AUTO] | J3: Balance [AUTO] | K3: Ret. % | L3: Status
A4: CON-001 | B4: Muhammad Arif | C4: Civil Works | D4: 03009876543 | E4: 0 | F4: =IFERROR(SUMIF('🏗️ Site Log'!B:B,A4,'🏗️ Site Log'!H:H),0) -> 0 | G4: =G4*L4 -> 0 | H4: =G4-H4 -> 0 | I4: =IFERROR(SUMIF('🧾 EXPENSES ← Enter Here'!G:G,B4,'🧾 EXPENSES ← Enter Here'!J:J),0) -> 0 | J4: =I4-J4 -> 0 | K4: 0.1 | L4: Active
A5: CON-002 | B5: Afzal | C5: Electrical | D5: 03334455667 | E5: 0 | F5: =IFERROR(SUMIF('🏗️ Site Log'!B:B,A5,'🏗️ Site Log'!H:H),0) -> 0 | G5: =G5*L5 -> 0 | H5: =G5-H5 -> 0 | I5: =IFERROR(SUMIF('🧾 EXPENSES ← Enter Here'!G:G,B5,'🧾 EXPENSES ← Enter Here'!J:J),0) -> 0 | J5: =I5-J5 -> 0 | K5: 0.1 | L5: Active

Sheet 📦 Materials
A1: 📦 MATERIAL MASTER — Stock auto from Purchases minus Site Log consumption
A2: N
A3: Material ID | B3: Name | C3: Category | D3: Unit | E3: Unit Cost | F3: Reorder Lvl | G3: Stock [AUTO] | H3: Stock Value [AUTO] | I3: Purchased [AUTO] | J3: Consumed [AUTO] | K3: Status [AUTO] | L3: Vendor ID
A4: M-001 | B4: OPC Cement 50kg | C4: Cement | D4: Bag | E4: 1000 | F4: 0 | G4: =IFERROR(SUMIF('📦 PURCHASES ← Enter Here'!E:E,A4,'📦 PURCHASES ← Enter Here'!H:H)-SUMIF('🏗️ Site Log'!E:E,A4,'🏗️ Site Log'!F:F),0) -> 0 | H4: =G4*E4 -> 0 | I4: =IFERROR(SUMIF('📦 PURCHASES ← Enter Here'!E:E,A4,'📦 PURCHASES ← Enter Here'!H:H),0) -> 0 | J4: =IFERROR(SUMIF('🏗️ Site Log'!E:E,A4,'🏗️ Site Log'!F:F),0) -> 0 | K4: =IF(G4<=F4,"LOW STOCK","OK") -> LOW STOCK | L4: V-001
A5: M-002 | B5: Steel Rebar 12mm | C5: Steel | D5: Tonne | E5: 180000 | F5: 0 | G5: =IFERROR(SUMIF('📦 PURCHASES ← Enter Here'!E:E,A5,'📦 PURCHASES ← Enter Here'!H:H)-SUMIF('🏗️ Site Log'!E:E,A5,'🏗️ Site Log'!F:F),0) -> 0 | H5: =G5*E5 -> 0 | I5: =IFERROR(SUMIF('📦 PURCHASES ← Enter Here'!E:E,A5,'📦 PURCHASES ← Enter Here'!H:H),0) -> 0 | J5: =IFERROR(SUMIF('🏗️ Site Log'!E:E,A5,'🏗️ Site Log'!F:F),0) -> 0 | K5: =IF(G5<=F5,"LOW STOCK","OK") -> LOW STOCK | L5: V-002
A6: M-003 | B6: Bricks Standard | C6: Masonry | D6: 1000 pcs | E6: 12000 | F6: 0 | G6: =IFERROR(SUMIF('📦 PURCHASES ← Enter Here'!E:E,A6,'📦 PURCHASES ← Enter Here'!H:H)-SUMIF('🏗️ Site Log'!E:E,A6,'🏗️ Site Log'!F:F),0) -> 0 | H6: =G6*E6 -> 0 | I6: =IFERROR(SUMIF('📦 PURCHASES ← Enter Here'!E:E,A6,'📦 PURCHASES ← Enter Here'!H:H),0) -> 0 | J6: =IFERROR(SUMIF('🏗️ Site Log'!E:E,A6,'🏗️ Site Log'!F:F),0) -> 0 | K6: =IF(G6<=F6,"LOW STOCK","OK") -> LOW STOCK | L6: V-001
A7: M-004 | B7: SRC Cement | C7: Cement | D7: 1000 pcs | E7: 15000 | F7: 0 | G7: =IFERROR(SUMIF('📦 PURCHASES ← Enter Here'!E:E,A7,'📦 PURCHASES ← Enter Here'!H:H)-SUMIF('🏗️ Site Log'!E:E,A7,'🏗️ Site Log'!F:F),0) -> 0 | H7: =G7*E7 -> 0 | I7: =IFERROR(SUMIF('📦 PURCHASES ← Enter Here'!E:E,A7,'📦 PURCHASES ← Enter Here'!H:H),0) -> 0 | J7: =IFERROR(SUMIF('🏗️ Site Log'!E:E,A7,'🏗️ Site Log'!F:F),0) -> 0 | K7: =IF(G7<=F7,"LOW STOCK","OK") -> LOW STOCK | L7: V-001

Sheet 📦 Inventory AUTO
A1: 📦 Inventory AUTO — Reads from Purchases - Site Log | DO NOT ENTER DATA
A2: P
A3: Inventory Value | E3: LOW STOCK | I3: OK
A4: =SUM(H7:H500) -> 0 | E4: =COUNTIF(K7:K500,"LOW STOCK") -> 4 | I4: =COUNTIF(K7:K500,"OK") -> 0
A6: ▌ STOCK LEVELS [AUTO]
A7: Mat. ID | B7: Name | C7: Category | D7: Unit | E7: Cost | F7: Reorder | G7: Stock [AUTO] | H7: Value [AUTO] | I7: Purchased | J7: Consumed | K7: Status | L7: Last Buy
A8: M-001 | B8: =IFERROR(VLOOKUP(A8,'📦 Materials'!A:B,2,0),"") -> OPC Cement 50kg | C8: =IFERROR(VLOOKUP(A8,'📦 Materials'!A:C,3,0),"") -> Cement | D8: =IFERROR(VLOOKUP(A8,'📦 Materials'!A:D,4,0),"") -> Bag | E8: =IFERROR(VLOOKUP(A8,'📦 Materials'!A:E,5,0),0) -> 1000 | F8: =IFERROR(VLOOKUP(A8,'📦 Materials'!A:F,6,0),0) -> 0 | G8: =IFERROR(SUMIF('📦 PURCHASES ← Enter Here'!F:F,A8,'📦 PURCHASES ← Enter Here'!I:I)-SUMIF('🏗️ Site Log'!E:E,A8,'🏗️ Site Log'!F:F),0) -> 0 | H8: =G8*E8 -> 0 | I8: =IFERROR(SUMIF('📦 PURCHASES ← Enter Here'!F:F,A8,'📦 PURCHASES ← Enter Here'!I:I),0) -> 0 | J8: =IFERROR(SUMIF('🏗️ Site Log'!E:E,A8,'🏗️ Site Log'!F:F),0) -> 0 | K8: =IF(G8<=F8,"LOW STOCK","OK") -> LOW STOCK | L8: =IFERROR(MAXIFS('📦 PURCHASES ← Enter Here'!C:C,'📦 PURCHASES ← Enter Here'!F:F,A8),"")
A9: M-002 | B9: =IFERROR(VLOOKUP(A9,'📦 Materials'!A:B,2,0),"") -> Steel Rebar 12mm | C9: =IFERROR(VLOOKUP(A9,'📦 Materials'!A:C,3,0),"") -> Steel | D9: =IFERROR(VLOOKUP(A9,'📦 Materials'!A:D,4,0),"") -> Tonne | E9: =IFERROR(VLOOKUP(A9,'📦 Materials'!A:E,5,0),0) -> 180000 | F9: =IFERROR(VLOOKUP(A9,'📦 Materials'!A:F,6,0),0) -> 0 | G9: =IFERROR(SUMIF('📦 PURCHASES ← Enter Here'!F:F,A9,'📦 PURCHASES ← Enter Here'!I:I)-SUMIF('🏗️ Site Log'!E:E,A9,'🏗️ Site Log'!F:F),0) -> 0 | H9: =G9*E9 -> 0 | I9: =IFERROR(SUMIF('📦 PURCHASES ← Enter Here'!F:F,A9,'📦 PURCHASES ← Enter Here'!I:I),0) -> 0 | J9: =IFERROR(SUMIF('🏗️ Site Log'!E:E,A9,'🏗️ Site Log'!F:F),0) -> 0 | K9: =IF(G9<=F9,"LOW STOCK","OK") -> LOW STOCK | L9: =IFERROR(MAXIFS('📦 PURCHASES ← Enter Here'!C:C,'📦 PURCHASES ← Enter Here'!F:F,A9),"")
A10: M-003 | B10: =IFERROR(VLOOKUP(A10,'📦 Materials'!A:B,2,0),"") -> Bricks Standard | C10: =IFERROR(VLOOKUP(A10,'📦 Materials'!A:C,3,0),"") -> Masonry | D10: =IFERROR(VLOOKUP(A10,'📦 Materials'!A:D,4,0),"") -> 1000 pcs | E10: =IFERROR(VLOOKUP(A10,'📦 Materials'!A:E,5,0),0) -> 12000 | F10: =IFERROR(VLOOKUP(A10,'📦 Materials'!A:F,6,0),0) -> 0 | G10: =IFERROR(SUMIF('📦 PURCHASES ← Enter Here'!F:F,A10,'📦 PURCHASES ← Enter Here'!I:I)-SUMIF('🏗️ Site Log'!E:E,A10,'🏗️ Site Log'!F:F),0) -> 0 | H10: =G10*E10 -> 0 | I10: =IFERROR(SUMIF('📦 PURCHASES ← Enter Here'!F:F,A10,'📦 PURCHASES ← Enter Here'!I:I),0) -> 0 | J10: =IFERROR(SUMIF('🏗️ Site Log'!E:E,A10,'🏗️ Site Log'!F:F),0) -> 0 | K10: =IF(G10<=F10,"LOW STOCK","OK") -> LOW STOCK | L10: =IFERROR(MAXIFS('📦 PURCHASES ← Enter Here'!C:C,'📦 PURCHASES ← Enter Here'!F:F,A10),"")
A11: M-004 | B11: =IFERROR(VLOOKUP(A11,'📦 Materials'!A:B,2,0),"") -> SRC Cement | C11: =IFERROR(VLOOKUP(A11,'📦 Materials'!A:C,3,0),"") -> Cement | D11: =IFERROR(VLOOKUP(A11,'📦 Materials'!A:D,4,0),"") -> 1000 pcs | E11: =IFERROR(VLOOKUP(A11,'📦 Materials'!A:E,5,0),0) -> 15000 | F11: =IFERROR(VLOOKUP(A11,'📦 Materials'!A:F,6,0),0) -> 0 | G11: =IFERROR(SUMIF('📦 PURCHASES ← Enter Here'!F:F,A11,'📦 PURCHASES ← Enter Here'!I:I)-SUMIF('🏗️ Site Log'!E:E,A11,'🏗️ Site Log'!F:F),0) -> 0 | H11: =G11*E11 -> 0 | I11: =IFERROR(SUMIF('📦 PURCHASES ← Enter Here'!F:F,A11,'📦 PURCHASES ← Enter Here'!I:I),0) -> 0 | J11: =IFERROR(SUMIF('🏗️ Site Log'!E:E,A11,'🏗️ Site Log'!F:F),0) -> 0 | K11: =IF(G11<=F11,"LOW STOCK","OK") -> LOW STOCK | L11: =IFERROR(MAXIFS('📦 PURCHASES ← Enter Here'!C:C,'📦 PURCHASES ← Enter Here'!F:F,A11),"")

Sheet 📦 PURCHASES ← Enter Here
A1: 📦 PURCHASES ← Enter Here — ONE ROW = Inventory Stock & Vendor Payable Auto-Update
A2: Material Name auto | Vendor Name auto | Stock auto-increases | Payable auto-increases
A3: ⚡ ENTER ONE ROW HERE. You do NOT need to update Inventory or Vendor Payables — they read from this sheet automatically.
A4: ▌ DATA ENTRY ZONE
A5: PO No. [AUTO] | B5: Serial [ENTER] | C5: Date [ENTER] | D5: Vendor ID [ENTER] | E5: Vendor Name [AUTO] | F5: Material ID [ENTER] | G5: Material Name [AUTO] | H5: Unit [AUTO] | I5: Qty [ENTER] | J5: Unit Cost [AUTO from Mat.] | K5: Total Cost [AUTO] | L5: Paid [ENTER] | M5: Balance [AUTO] | N5: Delivery Date [ENTER] | O5: Project ID [ENTER] | P5: Status [ENTER]
A6: =IF(B6<>"","PO-"&TEXT(B6,"000"),"") -> PO-001 | B6: 1 | C6: 2026-06-01 | D6: V-001 | E6: =IFERROR(VLOOKUP(D6,'🏪 Vendors'!A:B,2,0),"") -> Mansoor Ali | F6: M-001 | G6: =IFERROR(VLOOKUP(F6,'📦 Materials'!A:B,2,0),"") -> OPC Cement 50kg | H6: =IFERROR(VLOOKUP(F6,'📦 Materials'!A:D,4,0),"") -> Bag | I6: 0 | J6: =IFERROR(VLOOKUP(F6,'📦 Materials'!A:E,5,0),0) -> 1000 | K6: =I6*J6 -> 0 | L6: 0 | M6: =K6-L6 -> 0 | N6: 2026-06-10 | O6: PRJ-001 | P6: Delivered
A7: =IF(B7<>"","PO-"&TEXT(B7,"000"),"") -> PO-002 | B7: 2 | C7: 2026-06-05 | D7: V-002 | E7: =IFERROR(VLOOKUP(D7,'🏪 Vendors'!A:B,2,0),"") -> Saeed khan | F7: M-002 | G7: =IFERROR(VLOOKUP(F7,'📦 Materials'!A:B,2,0),"") -> Steel Rebar 12mm | H7: =IFERROR(VLOOKUP(F7,'📦 Materials'!A:D,4,0),"") -> Tonne | I7: 0 | J7: =IFERROR(VLOOKUP(F7,'📦 Materials'!A:E,5,0),0) -> 180000 | K7: =I7*J7 -> 0 | L7: 0 | M7: =K7-L7 -> 0 | N7: 2026-06-15 | O7: PRJ-001 | P7: Pending
A8: =IF(B8<>"","PO-"&TEXT(B8,"000"),"") -> PO-003 | B8: 3 | C8: 2026-06-05 | D8: V-001 | E8: =IFERROR(VLOOKUP(D8,'🏪 Vendors'!A:B,2,0),"") -> Mansoor Ali | F8: M-004 | G8: =IFERROR(VLOOKUP(F8,'📦 Materials'!A:B,2,0),"") -> SRC Cement | H8: =IFERROR(VLOOKUP(F8,'📦 Materials'!A:D,4,0),"") -> 1000 pcs | I8: 0 | J8: =IFERROR(VLOOKUP(F8,'📦 Materials'!A:E,5,0),0) -> 15000 | K8: =I8*J8 -> 0 | L8: 0 | M8: =K8-L8 -> 0 | N8: 2026-06-15 | O8: PRJ-001 | P8: Delivered

Sheet 🏗️ Site Log
A1: 🏗️ SITE LOG — Contractor Bills & Material Consumption
A2: Enter site activity. Inventory auto-reduces. Contractor payables auto-update.
A3: Log ID [AUTO] | B3: Contractor ID [ENTER] | C3: Project ID [ENTER] | D3: Activity [ENTER] | E3: Material ID [ENTER if used] | F3: Qty Used [ENTER] | G3: Unit [AUTO] | H3: Contractor Bill (PKR) [ENTER] | I3: Date [ENTER] | J3: Progress % [ENTER] | K3: Milestone [ENTER] | L3: Approved By [ENTER]
A4: =IF(B4<>"","CL-"&TEXT(B4,"000"),"") -> CL-CON-001 | B4: CON-001 | C4: PRJ-001 | D4: Foundation Work | E4: M-001 | F4: 0 | G4: =IFERROR(VLOOKUP(E4,'📦 Materials'!A:D,4,0),"") -> Bag | H4: 0 | I4: 2026-05-01 | J4: 0.15 | K4: Foundation Complete | L4: Ahmed M.

Sheet 📤 Payables AUTO
A1: 📤 Payables AUTO — Reads from Purchases & Expenses | DO NOT ENTER DATA
A2: R
A3: 🔒 AUTO SHEET — Reads from 📦 PURCHASES and 🧾 EXPENSES. No entry needed.
A4: ▌ VENDOR & CONTRACTOR PAYABLES
A5: Party Type | B5: ID | C5: Name | D5: Total Invoiced (PKR) | E5: Total Paid (PKR) | F5: Balance (PKR) | G5: Credit Days | H5: Last Purchase | I5: Status | J5: Notes
A6: Vendor | B6: V-001 | C6: =IFERROR(VLOOKUP(B6,'🏪 Vendors'!A:B,2,0),"") -> Mansoor Ali | D6: =IFERROR(SUMIF('📦 PURCHASES ← Enter Here'!D:D,B6,'📦 PURCHASES ← Enter Here'!K:K),0) -> 0 | E6: =IFERROR(SUMIF('📦 PURCHASES ← Enter Here'!D:D,B6,'📦 PURCHASES ← Enter Here'!L:L),0) -> 0 | F6: =D6-E6 -> 0 | G6: =IFERROR(VLOOKUP(B6,'🏪 Vendors'!A:H,8,0),0) -> 90 | H6: =IFERROR(MAXIFS('📦 PURCHASES ← Enter Here'!D:D,'📦 PURCHASES ← Enter Here'!C:C,B6),"") | I6: =IF(F6>0,"Pending","Cleared") -> Cleared
A7: Vendor | B7: V-002 | C7: =IFERROR(VLOOKUP(B7,'🏪 Vendors'!A:B,2,0),"") -> Saeed khan | D7: =IFERROR(SUMIF('📦 PURCHASES ← Enter Here'!D:D,B7,'📦 PURCHASES ← Enter Here'!K:K),0) -> 0 | E7: =IFERROR(SUMIF('📦 PURCHASES ← Enter Here'!D:D,B7,'📦 PURCHASES ← Enter Here'!L:L),0) -> 0 | F7: =D7-E7 -> 0 | G7: =IFERROR(VLOOKUP(B7,'🏪 Vendors'!A:H,8,0),0) -> 60 | H7: =IFERROR(MAXIFS('📦 PURCHASES ← Enter Here'!C:C,'📦 PURCHASES ← Enter Here'!C:C,B7),"") | I7: =IF(F7>0,"Pending","Cleared") -> Cleared
A8: Contractor | B8: CON-001 | C8: =IFERROR(VLOOKUP(B8,'👷 Contractors'!A:B,2,0),"") -> Muhammad Arif | D8: =IFERROR(SUMIF('🏗️ Site Log'!B:B,B8,'🏗️ Site Log'!H:H),0) -> 0 | E8: =IFERROR(SUMIF('🧾 EXPENSES ← Enter Here'!G:G,"BuildRight Const.",'🧾 EXPENSES ← Enter Here'!J:J),0) -> 0 | F8: =D8-E8 -> 0 | G8: 30 | I8: =IF(F8>0,"Pending","Cleared") -> Cleared | J8: Retention 10% withheld

Sheet 💳 PAYMENTS Entery
A1: 💳 PAYMENTS ← Enter Here — ONE ROW = Everything Updates Automatically
A2: ONE ROW = Receipt auto-numbers | Customer Name auto | Balance auto | Everything auto-updates
A3: ⚡ ENTER ONE ROW HERE. You do NOT need to update Installments, Bank Book, Cash Book, Receivables, P&L or Dashboard — they all read from this sheet automatically.
A4: Total Collected | G4: Bank Receipts | L4: Cash Receipts | Q4: This Month
A5: =SUM(H8:H49967) -> 2580000 | G5: =IFERROR(SUMIF(I8:I49967,"Bank Transfer",H8:H49967)+SUMIF(I8:I49967,"Cheque",H8:H49967)+SUMIF(I8:I49967,"Online Transfer",H8:H49967)+SUMIF(I8:I49967,"Pay Order",H8:H49967),0) -> 685000 | L5: =IFERROR(SUMIF(I8:I49967,"Cash",H8:H49967),0) -> 1895000 | Q5: =SUMPRODUCT((MONTH(C8:C4967)=MONTH(TODAY()))*(YEAR(C8:C4967)=YEAR(TODAY()))*H8:H4967) -> #VALUE!
A7: ▌ DATA ENTRY ZONE — Enter ONE row per payment. All other sheets update automatically.
A8: Receipt No. [AUTO] | B8: Serial [ENTER 1,2,3] | C8: Date | D8: Customer ID | E8: Customer Name [AUTO] | F8: Payment Type [ENTER] | G8: Flat ID | H8: Amount (PKR) | I8: Payment Mode | J8: Bank/Account | K8: Cheque/TT No. | L8: Installment Ref. | M8: Received By | N8: Notes [ENTER] | O8: Verified | P8: Inst. No. Covered [AUTO] | Q8: Running Total [AUTO] | R8: Outstanding [AUTO]
A9: ↓ Receipt No. auto-generates as R-001, R-002 etc. | Customer Name & Flat ID auto-fill from Customer ID | Outstanding auto-calculates
A11: =IF(B11<>"","RCP-"&TEXT(B11,"000"),"") -> RCP-001 | B11: 1 | C11: 46157 | D11: C-001 | E11: =IFERROR(VLOOKUP(D11,'👤 Customers'!A:C,3,0),"") -> Zulfiqar Ali Sapro | F11: Confirmation | G11: =IFERROR(VLOOKUP(D11,'👤 Customers'!A:K,11,0),"") -> 202 | H11: 385000 | I11: Bank Transfer | J11: Meezan Bank | K11: TT-2001 | L11: ='📅 Installments AUTO'!A11 -> F-202-01 | M11: Sharjeel | N11: Installment 1 payment | O11: Yes | P11: =IFERROR(COUNTIFS('📅 Installments AUTO'!C:C,G11,'📅 Installments AUTO'!N:N,"Paid"),"") -> 0 | Q11: =IFERROR(SUMIF(G$11:G11,G11,H$11:H11),0) -> 385000 | R11: =IFERROR(VLOOKUP(G11,'🏘️ Flat Register'!A:H,8,0)-Q11,0) -> 5285000
A12: =IF(B12<>"","R-"&TEXT(B12,"000"),"") -> R-002 | B12: 2 | C12: 46188 | D12: C-001 | E12: =IFERROR(VLOOKUP(D12,'👤 Customers'!A:C,3,0),"") -> Zulfiqar Ali Sapro | F12: Allocation | G12: =IFERROR(VLOOKUP(D12,'👤 Customers'!A:K,11,0),"") -> 202 | H12: 1190000 | I12: Cash | J12: Cash | L12: ='📅 Installments AUTO'!A11 -> F-202-01 | M12: Sharjeel | N12: Installment 1 payment | O12: Yes | P12: =IFERROR(COUNTIFS('📅 Installments AUTO'!C:C,G12,'📅 Installments AUTO'!N:N,"Paid"),"") -> 0 | Q12: =IFERROR(SUMIF(G$11:G12,G12,H$11:H12),0) -> 1575000 | R12: =IFERROR(VLOOKUP(G12,'🏘️ Flat Register'!A:H,8,0)-Q12,0) -> 4095000
A13: =IF(B13<>"","R-"&TEXT(B13,"000"),"") -> R-003 | B13: 3 | C13: 46218 | D13: C-001 | E13: =IFERROR(VLOOKUP(D13,'👤 Customers'!A:C,3,0),"") -> Zulfiqar Ali Sapro | F13: Installment | G13: =IFERROR(VLOOKUP(D13,'👤 Customers'!A:K,11,0),"") -> 202 | H13: 150000 | I13: Cash | J13: Cash | L13: ='📅 Installments AUTO'!A11 -> F-202-01 | M13: Sharjeel | N13: Installment 1 payment | O13: Yes | P13: =IFERROR(COUNTIFS('📅 Installments AUTO'!C:C,G13,'📅 Installments AUTO'!N:N,"Paid"),"") -> 0 | Q13: =IFERROR(SUMIF(G$11:G13,G13,H$11:H13),0) -> 1725000 | R13: =IFERROR(VLOOKUP(G13,'🏘️ Flat Register'!A:H,8,0)-Q13,0) -> 3945000
A14: =IF(B14<>"","R-"&TEXT(B14,"000"),"") -> R-004 | B14: 4 | C14: 46249 | D14: C-001 | E14: =IFERROR(VLOOKUP(D14,'👤 Customers'!A:C,3,0),"") -> Zulfiqar Ali Sapro | F14: Installment | G14: =IFERROR(VLOOKUP(D14,'👤 Customers'!A:K,11,0),"") -> 202 | H14: 275000 | I14: Cash | J14: Cash | L14: ='📅 Installments AUTO'!A11 -> F-202-01 | M14: Sharjeel | N14: Installment 1 payment | O14: Yes | P14: =IFERROR(COUNTIFS('📅 Installments AUTO'!C:C,G14,'📅 Installments AUTO'!N:N,"Paid"),"") -> 0 | Q14: =IFERROR(SUMIF(G$11:G14,G14,H$11:H14),0) -> 2000000 | R14: =IFERROR(VLOOKUP(G14,'🏘️ Flat Register'!A:H,8,0)-Q14,0) -> 3670000
A15: =IF(B15<>"","R-"&TEXT(B15,"000"),"") -> R-005 | B15: 5 | C15: 46280 | D15: C-001 | E15: =IFERROR(VLOOKUP(D15,'👤 Customers'!A:C,3,0),"") -> Zulfiqar Ali Sapro | F15: Installment | G15: =IFERROR(VLOOKUP(D15,'👤 Customers'!A:K,11,0),"") -> 202 | H15: 280000 | I15: Cash | J15: Cash | L15: ='📅 Installments AUTO'!A12 -> F-202-02 | M15: Sharjeel | N15: Installment 1 payment, same recp | O15: Yes | P15: =IFERROR(COUNTIFS('📅 Installments AUTO'!C:C,G15,'📅 Installments AUTO'!N:N,"Paid"),"") -> 0 | Q15: =IFERROR(SUMIF(G$11:G15,G15,H$11:H15),0) -> 2280000 | R15: =IFERROR(VLOOKUP(G15,'🏘️ Flat Register'!A:H,8,0)-Q15,0) -> 3390000
A16: =IF(B16<>"","R-"&TEXT(B16,"000"),"") -> R-006 | B16: 6 | D16: C-001 | E16: =IFERROR(VLOOKUP(D16,'👤 Customers'!A:C,3,0),"") -> Zulfiqar Ali Sapro | F16: Installment | G16: =IFERROR(VLOOKUP(D16,'👤 Customers'!A:K,11,0),"") -> 202 | H16: 150000 | I16: Online Transfer | J16: HBL | K16: 4525 | P16: =IFERROR(COUNTIFS('📅 Installments AUTO'!C:C,G16,'📅 Installments AUTO'!N:N,"Paid"),"") -> 0 | Q16: =IFERROR(SUMIF(G$11:G16,G16,H$11:H16),0) -> 2430000 | R16: =IFERROR(VLOOKUP(G16,'🏘️ Flat Register'!A:H,8,0)-Q16,0) -> 3240000
A17: =IF(B17<>"","R-"&TEXT(B17,"000"),"") | E17: =IFERROR(VLOOKUP(D17,'👤 Customers'!A:C,2,0),"") | F17: Membership Fee | G17: =IFERROR(VLOOKUP(D17,'👤 Customers'!A:K,10,0),"") | H17: 150000 | I17: Online Transfer | J17: HBL | P17: =IFERROR(COUNTIFS('📅 Installments AUTO'!C:C,G17,'📅 Installments AUTO'!N:N,"Paid"),"") -> 0 | Q17: =IFERROR(SUMIF(G$11:G17,G17,H$11:H17),0) -> 150000 | R17: =IFERROR(VLOOKUP(G17,'🏘️ Flat Register'!A:H,8,0)-Q17,0) -> 0
A18: =IF(B18<>"","R-"&TEXT(B18,"000"),"") | E18: =IFERROR(VLOOKUP(D18,'👤 Customers'!A:C,2,0),"") | F18: Membership Fee | G18: =IFERROR(VLOOKUP(D18,'👤 Customers'!A:K,10,0),"") | P18: =IFERROR(COUNTIFS('📅 Installments AUTO'!C:C,G18,'📅 Installments AUTO'!N:N,"Paid"),"") -> 0 | Q18: =IFERROR(SUMIF(G$11:G18,G18,H$11:H18),0) -> 150000 | R18: =IFERROR(VLOOKUP(G18,'🏘️ Flat Register'!A:H,8,0)-Q18,0) -> 0
A19: =IF(B19<>"","R-"&TEXT(B19,"000"),"") | E19: =IFERROR(VLOOKUP(D19,'👤 Customers'!A:C,2,0),"") | F19: Membership Fee | G19: =IFERROR(VLOOKUP(D19,'👤 Customers'!A:K,10,0),"") | P19: =IFERROR(COUNTIFS('📅 Installments AUTO'!C:C,G19,'📅 Installments AUTO'!N:N,"Paid"),"") -> 0 | Q19: =IFERROR(SUMIF(G$11:G19,G19,H$11:H19),0) -> 150000 | R19: =IFERROR(VLOOKUP(G19,'🏘️ Flat Register'!A:H,8,0)-Q19,0) -> 0

Sheet 🏦 Bank Book AUTO
A1: 🏦 Bank Book AUTO — Reads from Payments + Expenses | DO NOT ENTER DATA
A2: P
A3: 🔒 AUTO SHEET — Bank balance reads from 💳 PAYMENTS (receipts) and 🧾 EXPENSES (payments). Nothing to enter here.
A4: ▌ BANK ACCOUNT BALANCES [AUTO] | N4: 🔒 AUTO SHEET — Cash balance reads automatically from 💳 PAYMENTS (cash receipts) and 🧾 EXPENSES (cash payments).
A5: Account | B5: Opening Bal. | C5: Total Receipts [AUTO] | D5: Total Expense | E5: Closing Balance [AUTO] | F5: Type | N5: Opening Cash Balance | Q5: 0
A6: Meezan Bank | B6: 0 | C6: =IFERROR(SUMIF('💳 PAYMENTS Entery'!J:J,"Meezan Bank",'💳 PAYMENTS Entery'!H:H),0) -> 385000 | D6: =IFERROR(SUMIF('🧾 EXPENSES ← Enter Here'!H:H,"Meezan Bank",'🧾 EXPENSES ← Enter Here'!J:J),0) -> 0 | E6: =B6+C6-D6 -> 385000 | F6: Current | N6: Cash Receipts [AUTO] | Q6: =IFERROR(SUMIF('💳 PAYMENTS Entery'!V:V,"Cash",'💳 PAYMENTS Entery'!U:U),0) -> 0
A7: HBL | B7: 0 | C7: =IFERROR(SUMIF('💳 PAYMENTS Entery'!J:J,"HBL",'💳 PAYMENTS Entery'!H:H),0) -> 300000 | D7: =IFERROR(SUMIF('🧾 EXPENSES ← Enter Here'!H:H,"HBL",'🧾 EXPENSES ← Enter Here'!J:J),0) -> 4000000 | E7: =B7+C7-D7 -> -3700000 | F7: Current | N7: Cash Payments [AUTO] | Q7: =IFERROR(SUMIF('🧾 EXPENSES ← Enter Here'!U:U,"Cash",'🧾 EXPENSES ← Enter Here'!W:W),0) -> 0
A8: CASH | B8: 0 | C8: =IFERROR(SUMIF('💳 PAYMENTS Entery'!J:J,"CASH",'💳 PAYMENTS Entery'!H:H),0) -> 1895000 | D8: =IFERROR(SUMIF('🧾 EXPENSES ← Enter Here'!H:H,"CASH",'🧾 EXPENSES ← Enter Here'!J:J),0) -> 60000 | E8: =B8+C8-D8 -> 1835000 | F8: Current | N8: CLOSING CASH BALANCE [AUTO] | Q8: =Q5+Q6-Q7 -> 0
A9: Other | B9: 0 | C9: =IFERROR(SUMIF('💳 PAYMENTS Entery'!J:J,"Other",'💳 PAYMENTS Entery'!H:H),0) -> 0 | D9: =IFERROR(SUMIF('🧾 EXPENSES ← Enter Here'!H:H,"other",'🧾 EXPENSES ← Enter Here'!J:J),0) -> 0 | E9: =B9+C9-D9 -> 0 | F9: Current
A12: TOTAL NET BANK BALANCE [AUTO] | E12: =SUM(E6:E7) -> -3315000
A13: TOTAL NET CASH BALANCE [AUTO] | E13: =E8 -> 1835000
A15: ▌ TRANSACTION DETAIL — Auto from Payments + Expenses
A16: Date | B16: Description | C16: Source | D16: Receipt (PKR) | E16: Payment (PKR) | F16: Balance (PKR) | G16: Ref
A17: 2026-01-15 | B17: Partner Capital Ahmed — Meezan Bank | C17: 👥 Partners | D17: 50000000 | E17: 0 | F17: =D17-E17 -> 50000000 | G17: PC-001
A18: 2026-06-01 | B18: Customer Payment Ali Khan — Bank Transfer | C18: 💳 PAYMENTS | D18: 500000 | E18: 0 | F18: =F17+D18-E18 -> 50500000 | G18: R-001
A19: 2026-06-03 | B19: Cement Purchase — ABC Cement Co. | C19: 🧾 EXPENSES | D19: 0 | E19: 250000 | F19: =F18+D19-E19 -> 50250000 | G19: PV-001

Sheet 💵 Cash Book AUTO
A1: 💵 Cash Book AUTO — Reads from Payments + Expenses | DO NOT ENTER DATA
A2: I
A3: 🔒 AUTO SHEET — Cash balance reads automatically from 💳 PAYMENTS (cash receipts) and 🧾 EXPENSES (cash payments).
A4: Opening Cash Balance | D4: 0
A5: Cash Receipts [AUTO] | D5: =IFERROR(SUMIF('💳 PAYMENTS Entery'!I:I,"Cash",'💳 PAYMENTS Entery'!H:H),0) -> 1895000
A6: Cash Payments [AUTO] | D6: =IFERROR(SUMIF('🧾 EXPENSES ← Enter Here'!H:H,"Cash",'🧾 EXPENSES ← Enter Here'!J:J),0) -> 60000
A7: CLOSING CASH BALANCE [AUTO] | D7: =D4+D5-D6 -> 1835000

Sheet 📒 General Ledger AUTO
A1: 📒 General Ledger AUTO — Double-Entry Auto-Generated | DO NOT ENTER DATA
A2: P
A3: 🔒 AUTO SHEET — Journal entries auto-generated from Payments and Expenses sheets.
A4: Total Debits | E4: Total Credits | I4: Balance Check
A5: =SUM(H8:H50000) -> 101850000 | E5: =SUM(I8:I50000) -> 101950000 | I5: =IF(ABS(D5-H5)<1,"BALANCED","OUT OF BALANCE") -> BALANCED
A7: ▌ JOURNAL ENTRIES [AUTO]
A8: JV No. | B8: Date | C8: Acct Code | D8: Account Name | E8: Description | F8: Ref | G8: Source | H8: Debit (PKR) | I8: Credit (PKR) | J8: Balance (PKR) | K8: Posted By
A9: JV-001 | B9: 2026-01-15 | C9: 1100 | D9: Cash & Bank | E9: Partner Capital Ahmed | F9: PC-001 | G9: Partners | H9: 50000000 | I9: 0 | J9: =H9-I9 -> 50000000 | K9: Admin
A10: JV-002 | B10: 2026-01-15 | C10: 3100 | D10: Partner Capital | E10: Capital Ahmed | F10: PC-001 | G10: Partners | H10: 0 | I10: 50000000 | J10: =J9+H10-I10 -> 0 | K10: Admin
A11: JV-003 | B11: 2026-01-15 | C11: 1100 | D11: Cash & Bank | E11: Partner Capital Taufeeq | F11: PC-002 | G11: Partners | H11: 50000000 | I11: 0 | J11: =J10+H11-I11 -> 50000000 | K11: Admin
A12: JV-004 | B12: 2026-01-15 | C12: 3100 | D12: Partner Capital | E12: Capital Taufeeq | F12: PC-002 | G12: Partners | H12: 0 | I12: 50000000 | J12: =J11+H12-I12 -> 0 | K12: Admin
A13: JV-005 | B13: 2026-06-01 | C13: 1100 | D13: Cash & Bank | E13: Customer Receipt Ali Khan | F13: R-001 | G13: 💳 PAYMENTS | H13: 500000 | I13: 0 | J13: =J12+H13-I13 -> 500000 | K13: Admin
A14: JV-006 | B14: 2026-06-01 | C14: 1200 | D14: Receivables | E14: Sale booked F-101 | F14: R-001 | G14: 💳 PAYMENTS | H14: 0 | I14: 500000 | J14: =J13+H14-I14 -> 0 | K14: Admin
A15: JV-007 | B15: 2026-06-02 | C15: 1100 | D15: Cash & Bank | E15: Customer Receipt Sara Ahmed | F15: R-002 | G15: 💳 PAYMENTS | H15: 1000000 | I15: 0 | J15: =J14+H15-I15 -> 1000000 | K15: Admin
A16: JV-008 | B16: 2026-06-02 | C16: 1200 | D16: Receivables | E16: Sale booked F-102 | F16: R-002 | G16: 💳 PAYMENTS | H16: 0 | I16: 1000000 | J16: =J15+H16-I16 -> 0 | K16: Admin
A17: JV-009 | B17: 2026-06-03 | C17: 5100 | D17: Construction Expenses | E17: Cement Purchase | F17: PV-001 | G17: 🧾 EXPENSES | H17: 250000 | I17: 0 | J17: =J16+H17-I17 -> 250000 | K17: Admin
A18: JV-010 | B18: 2026-06-03 | C18: 1100 | D18: Cash & Bank | E18: Payment ABC Cement | F18: PV-001 | G18: 🧾 EXPENSES | H18: 0 | I18: 250000 | J18: =J17+H18-I18 -> 0 | K18: Admin
A19: JV-011 | B19: 2026-06-05 | C19: 5200 | D19: Labor Cost | E19: Site Wages W22 | F19: PV-002 | G19: 🧾 EXPENSES | H19: 100000 | I19: 0 | J19: =J18+H19-I19 -> 100000 | K19: Admin
A20: JV-012 | B20: 2026-06-05 | C20: 1100 | D20: Cash & Bank | E20: Cash wages paid | F20: PV-002 | G20: 🧾 EXPENSES | H20: 0 | I20: 100000 | J20: =J19+H20-I20 -> 0 | K20: Admin
A21: JV-013 | B21: 2026-06-05 | C21: 1100 | D21: Cash & Bank | E21: Cash wages paid | F21: PV-002 | G21: 🧾 EXPENSES | H21: 0 | I21: 100000 | J21: =J20+H21-I21 -> -100000 | K21: Admin

Sheet ⚖️ Trial Balance AUTO
A1: ⚖️ Trial Balance AUTO — As at 15 July 2026 | DO NOT ENTER DATA
A2: L
A3: Total Debits | D3: Total Credits | G3: Balance Check
A4: =SUM(D7:D30) -> 203700000 | D4: =SUM(E7:E30) -> 203900000 | G4: =IF(ABS(B4-E4)<1,"BALANCED","OUT OF BALANCE") -> BALANCED
A6: Acct Code | B6: Account Name | C6: Type | D6: Debit (PKR) | E6: Credit (PKR) | F6: Net (PKR)
A7: 1100 | B7: Cash & Bank | C7: Asset | D7: =SUMIF('📒 General Ledger AUTO'!C:C,A7,'📒 General Ledger AUTO'!H:H) -> 101500000 | E7: =SUMIF('📒 General Ledger AUTO'!C:C,A7,'📒 General Ledger AUTO'!I:I) -> 450000 | F7: =D7-E7 -> 101050000
A8: 1200 | B8: Receivables | C8: Asset | D8: =SUMIF('📒 General Ledger AUTO'!C:C,A8,'📒 General Ledger AUTO'!H:H) -> 0 | E8: =SUMIF('📒 General Ledger AUTO'!C:C,A8,'📒 General Ledger AUTO'!I:I) -> 1500000 | F8: =D8-E8 -> -1500000
A9: 1300 | B9: Inventory | C9: Asset | D9: 0 | E9: 0 | F9: =D9-E9 -> 0
A10: 2100 | B10: Trade Payables | C10: Liability | D10: 0 | E10: 0 | F10: =D10-E10 -> 0
A11: 3100 | B11: Partner Capital | C11: Equity | D11: =SUMIF('📒 General Ledger AUTO'!C:C,A11,'📒 General Ledger AUTO'!H:H) -> 0 | E11: =SUMIF('📒 General Ledger AUTO'!C:C,A11,'📒 General Ledger AUTO'!I:I) -> 100000000 | F11: =D11-E11 -> -100000000
A12: 5100 | B12: Construction Cost | C12: Expense | D12: =SUMIF('📒 General Ledger AUTO'!C:C,A12,'📒 General Ledger AUTO'!H:H) -> 250000 | E12: =SUMIF('📒 General Ledger AUTO'!C:C,A12,'📒 General Ledger AUTO'!I:I) -> 0 | F12: =D12-E12 -> 250000
A13: 5200 | B13: Labor Cost | C13: Expense | D13: =SUMIF('📒 General Ledger AUTO'!C:C,A13,'📒 General Ledger AUTO'!H:H) -> 100000 | E13: =SUMIF('📒 General Ledger AUTO'!C:C,A13,'📒 General Ledger AUTO'!I:I) -> 0 | F13: =D13-E13 -> 100000
A14: 5300 | B14: Admin | C14: Expense | D14: 0 | E14: 0 | F14: =D14-E14 -> 0
A15: 5400 | B15: Marketing | C15: Expense | D15: 0 | E15: 0 | F15: =D15-E15 -> 0
A16: 5500 | B16: Salaries | C16: Expense | D16: 0 | E16: 0 | F16: =D16-E16 -> 0
A17: TOTAL | D17: =SUM(D7:D16) -> 101850000 | E17: =SUM(E7:E16) -> 101950000 | F17: =D17-E17 -> -100000

Sheet 📊 P&L AUTO
A1: 📊 P&L AUTO — Period Ending 15 July 2026 | DO NOT ENTER DATA
A2: I
A3: REVENUE
A4: Flat Sales | H4: =IFERROR(SUMIF('🏘️ Flat Register'!L:L,"Sold",'🏘️ Flat Register'!H:H),0) -> 5670000
A5: Other Income | H5: 0
A6: TOTAL REVENUE | H6: =SUM(H4:H5) -> 5670000
A8: COST OF CONSTRUCTION
A9: Material | H9: =IFERROR(SUMIF('🧾 EXPENSES ← Enter Here'!E:E,"Material",'🧾 EXPENSES ← Enter Here'!J:J),0) -> 0
A10: Labor | H10: =IFERROR(SUMIF('🧾 EXPENSES ← Enter Here'!E:E,"Labor",'🧾 EXPENSES ← Enter Here'!J:J),0) -> 0
A11: Contractor | H11: =IFERROR(SUMIF('🧾 EXPENSES ← Enter Here'!E:E,"Contractor",'🧾 EXPENSES ← Enter Here'!J:J),0) -> 0
A12: Equipment | H12: =IFERROR(SUMIF('🧾 EXPENSES ← Enter Here'!E:E,"Equipment",'🧾 EXPENSES ← Enter Here'!J:J),0) -> 0
A13: Utilities | H13: =IFERROR(SUMIF('🧾 EXPENSES ← Enter Here'!E:E,"Utilities",'🧾 EXPENSES ← Enter Here'!J:J),0) -> 0
A14: TOTAL CONSTRUCTION COST | H14: =SUM(H9:H13) -> 0
A15: GROSS PROFIT | H15: =H6-H14 -> 5670000
A17: OPERATING EXPENSES
A18: Salaries | H18: =IFERROR(SUMIF('🧾 EXPENSES ← Enter Here'!E:E,"Salary",'🧾 EXPENSES ← Enter Here'!J:J),0) -> 0
A19: Admin | H19: =IFERROR(SUMIF('🧾 EXPENSES ← Enter Here'!E:E,"Admin",'🧾 EXPENSES ← Enter Here'!J:J),0) -> 0
A20: Marketing | H20: =IFERROR(SUMIF('🧾 EXPENSES ← Enter Here'!E:E,"Marketing",'🧾 EXPENSES ← Enter Here'!J:J),0) -> 0
A21: Legal & Professional | H21: =IFERROR(SUMIF('🧾 EXPENSES ← Enter Here'!E:E,"Legal",'🧾 EXPENSES ← Enter Here'!J:J)+SUMIF('🧾 EXPENSES ← Enter Here'!E:E,"Professional",'🧾 EXPENSES ← Enter Here'!J:J),0) -> 0
A22: Other | H22: =IFERROR(SUMIF('🧾 EXPENSES ← Enter Here'!E:E,"Other",'🧾 EXPENSES ← Enter Here'!J:J),0) -> 4060000
A23: TOTAL OPERATING EXPENSES | H23: =SUM(H18:H22) -> 4060000
A24: OPERATING PROFIT | H24: =H15-H23 -> 1610000
A26: FINAL
A27: Tax Provision | H27: 0
A28: Adjustments | H28: 0
A29: NET PROFIT / (LOSS) | H29: =H24-SUM(H27:H28) -> 1610000
A30: Ahmed Malik 50% | H30: =IFERROR(H29*0.5,0) -> 805000
A31: Taufeeq Baig 50% | H31: =IFERROR(H29*0.5,0) -> 805000
A32: NET PROFIT (for partner calc) | H32: =H29 -> 1610000

Sheet 🏛️ Balance Sheet AUTO
A1: 🏛️ Balance Sheet AUTO — As at 15 July 2026 | DO NOT ENTER DATA
A2: I
A3: ASSETS
A4: Current Assets
A5: Cash & Bank | H5: ='🏦 Bank Book AUTO'!E12+'💵 Cash Book AUTO'!D7 -> -1480000
A6: Receivables | H6: =IFERROR(SUMIF('📅 Installments AUTO'!N:N,"Pending",'📅 Installments AUTO'!K:K)+SUMIF('📅 Installments AUTO'!N:N,"Overdue",'📅 Installments AUTO'!K:K),0) -> 3200000
A7: Other Current | H7: 0
A8: TOTAL CURRENT ASSETS | H8: =SUM(H5:H7) -> 1720000
A10: Non-Current Assets
A11: WIP Construction | H11: =IFERROR(SUMIF('🧾 EXPENSES ← Enter Here'!E:E,"Material",'🧾 EXPENSES ← Enter Here'!J:J)+SUMIF('🧾 EXPENSES ← Enter Here'!E:E,"Contractor",'🧾 EXPENSES ← Enter Here'!J:J),0) -> 0
A12: Inventory at Site | H12: =IFERROR(SUMPRODUCT('📦 Materials'!G4:G100*'📦 Materials'!E4:E100),0) -> 0
A13: Fixed Assets | H13: 0
A14: TOTAL NON-CURRENT ASSETS | H14: =SUM(H11:H13) -> 0
A15: TOTAL ASSETS | H15: =H8+H14 -> 1720000
A17: LIABILITIES
A18: Current Liabilities
A19: Vendor Payables | H19: =IFERROR(SUM('📤 Payables AUTO'!F6:F500),0) -> 0
A20: Contractor Payables | H20: =IFERROR(SUM('👷 Contractors'!J:J),0) -> 0
A21: Other Liabilities | H21: 0
A22: TOTAL LIABILITIES | H22: =SUM(H19:H21) -> 5000000
A24: EQUITY
A25: Partner Capital | H25: =IFERROR(SUM('👥 Partners'!F8:F12),0) -> 2000000
A26: Net Profit | H26: ='📊 P&L AUTO'!H32 -> 1610000
A27: Less: Withdrawals | H27: =-IFERROR(SUM('👥 Partners'!I8:I12),0) -> 0
A28: TOTAL EQUITY | H28: =SUM(H25:H27) -> 3610000
A29: TOTAL LIABILITIES + EQUITY | H29: =H22+H28 -> 129100400
A31: BALANCE CHECK | H31: =IF(ABS(H15-H29)<1,"BALANCED","OUT OF BALANCE") -> OUT OF BALANCE

Sheet 📈 Sales AUTO
A1: 📈 Sales AUTO — Reads from Flat Master + Payments | DO NOT ENTER DATA
A2: T
A3: Total Sales | F3: Collected | K3: Outstanding | P3: Collection %
A4: =SUMIF('🏘️ Flat Register'!L:L,"Sold",'🏘️ Flat Register'!H:H) -> 5670000 | F4: =SUM('💳 PAYMENTS Entery'!H11:H49967) -> 2580000 | K4: =A4-F4 -> 3090000 | P4: =IFERROR(F4/A4,0) -> 0.45502646
A6: ▌ FLAT-WISE SALES DETAIL
A7: Flat ID | B7: Tower | C7: Floor | D7: Area sqft | E7: Sale Price (PKR) | F7: Status | G7: Customer | H7: Booking Date | I7: Received (PKR) | J7: Outstanding (PKR) | K7: % Paid
A8: F-01 | B8: =IFERROR(VLOOKUP(A8,'🏘️ Flat Register'!A:C,3,0),"") | C8: =IFERROR(VLOOKUP(A8,'🏘️ Flat Register'!A:D,4,0),0) -> 0 | D8: =IFERROR(VLOOKUP(A8,'🏘️ Flat Register'!A:F,6,0),0) -> 0 | E8: =IFERROR(VLOOKUP(A8,'🏘️ Flat Register'!A:H,8,0),0) -> 0 | F8: =IFERROR(VLOOKUP(A8,'🏘️ Flat Register'!A:L,9,0),"") | G8: =IFERROR(VLOOKUP(A8,'🏘️ Flat Register'!A:N,11,0),"") | H8: =IFERROR(VLOOKUP(A8,'🏘️ Flat Register'!A:O,12,0),"") | I8: =IFERROR(SUMIF('💳 PAYMENTS Entery'!G:G,A8,'💳 PAYMENTS Entery'!H:H),0) -> 0 | J8: =IFERROR(E8-I8,0) -> 0 | K8: =IFERROR(I8/E8,0) -> 0
A9: F-02 | B9: =IFERROR(VLOOKUP(A9,'🏘️ Flat Register'!A:C,3,0),"") | C9: =IFERROR(VLOOKUP(A9,'🏘️ Flat Register'!A:D,4,0),0) -> 0 | D9: =IFERROR(VLOOKUP(A9,'🏘️ Flat Register'!A:F,6,0),0) -> 0 | E9: =IFERROR(VLOOKUP(A9,'🏘️ Flat Register'!A:H,8,0),0) -> 0 | F9: =IFERROR(VLOOKUP(A9,'🏘️ Flat Register'!A:L,9,0),"") | G9: =IFERROR(VLOOKUP(A9,'🏘️ Flat Register'!A:N,11,0),"") | H9: =IFERROR(VLOOKUP(A9,'🏘️ Flat Register'!A:O,12,0),"") | I9: =IFERROR(SUMIF('💳 PAYMENTS Entery'!G:G,A9,'💳 PAYMENTS Entery'!H:H),0) -> 0 | J9: =IFERROR(E9-I9,0) -> 0 | K9: =IFERROR(I9/E9,0) -> 0
A10: F-101 | B10: =IFERROR(VLOOKUP(A10,'🏘️ Flat Register'!A:C,3,0),"") | C10: =IFERROR(VLOOKUP(A10,'🏘️ Flat Register'!A:D,4,0),0) -> 0 | D10: =IFERROR(VLOOKUP(A10,'🏘️ Flat Register'!A:F,6,0),0) -> 0 | E10: =IFERROR(VLOOKUP(A10,'🏘️ Flat Register'!A:H,8,0),0) -> 0 | F10: =IFERROR(VLOOKUP(A10,'🏘️ Flat Register'!A:L,9,0),"") | G10: =IFERROR(VLOOKUP(A10,'🏘️ Flat Register'!A:N,11,0),"") | H10: =IFERROR(VLOOKUP(A10,'🏘️ Flat Register'!A:O,12,0),"") | I10: =IFERROR(SUMIF('💳 PAYMENTS Entery'!G:G,A10,'💳 PAYMENTS Entery'!H:H),0) -> 0 | J10: =IFERROR(E10-I10,0) -> 0 | K10: =IFERROR(I10/E10,0) -> 0
A11: F-102 | B11: =IFERROR(VLOOKUP(A11,'🏘️ Flat Register'!A:C,3,0),"") | C11: =IFERROR(VLOOKUP(A11,'🏘️ Flat Register'!A:D,4,0),0) -> 0 | D11: =IFERROR(VLOOKUP(A11,'🏘️ Flat Register'!A:F,6,0),0) -> 0 | E11: =IFERROR(VLOOKUP(A11,'🏘️ Flat Register'!A:H,8,0),0) -> 0 | F11: =IFERROR(VLOOKUP(A11,'🏘️ Flat Register'!A:L,9,0),"") | G11: =IFERROR(VLOOKUP(A11,'🏘️ Flat Register'!A:N,11,0),"") | H11: =IFERROR(VLOOKUP(A11,'🏘️ Flat Register'!A:O,12,0),"") | I11: =IFERROR(SUMIF('💳 PAYMENTS Entery'!G:G,A11,'💳 PAYMENTS Entery'!H:H),0) -> 0 | J11: =IFERROR(E11-I11,0) -> 0 | K11: =IFERROR(I11/E11,0) -> 0
A12: F-201 | B12: =IFERROR(VLOOKUP(A12,'🏘️ Flat Register'!A:C,3,0),"") | C12: =IFERROR(VLOOKUP(A12,'🏘️ Flat Register'!A:D,4,0),0) -> 0 | D12: =IFERROR(VLOOKUP(A12,'🏘️ Flat Register'!A:F,6,0),0) -> 0 | E12: =IFERROR(VLOOKUP(A12,'🏘️ Flat Register'!A:H,8,0),0) -> 0 | F12: =IFERROR(VLOOKUP(A12,'🏘️ Flat Register'!A:L,9,0),"") | G12: =IFERROR(VLOOKUP(A12,'🏘️ Flat Register'!A:N,11,0),"") | H12: =IFERROR(VLOOKUP(A12,'🏘️ Flat Register'!A:O,12,0),"") | I12: =IFERROR(SUMIF('💳 PAYMENTS Entery'!G:G,A12,'💳 PAYMENTS Entery'!H:H),0) -> 0 | J12: =IFERROR(E12-I12,0) -> 0 | K12: =IFERROR(I12/E12,0) -> 0
A13: F-202 | B13: =IFERROR(VLOOKUP(A13,'🏘️ Flat Register'!A:C,3,0),"") | C13: =IFERROR(VLOOKUP(A13,'🏘️ Flat Register'!A:D,4,0),0) -> 0 | D13: =IFERROR(VLOOKUP(A13,'🏘️ Flat Register'!A:F,6,0),0) -> 0 | E13: =IFERROR(VLOOKUP(A13,'🏘️ Flat Register'!A:H,8,0),0) -> 0 | F13: =IFERROR(VLOOKUP(A13,'🏘️ Flat Register'!A:L,9,0),"") | G13: =IFERROR(VLOOKUP(A13,'🏘️ Flat Register'!A:N,11,0),"") | H13: =IFERROR(VLOOKUP(A13,'🏘️ Flat Register'!A:O,12,0),"") | I13: =IFERROR(SUMIF('💳 PAYMENTS Entery'!G:G,A13,'💳 PAYMENTS Entery'!H:H),0) -> 0 | J13: =IFERROR(E13-I13,0) -> 0 | K13: =IFERROR(I13/E13,0) -> 0
A14: F-301 | B14: =IFERROR(VLOOKUP(A14,'🏘️ Flat Register'!A:C,3,0),"") | C14: =IFERROR(VLOOKUP(A14,'🏘️ Flat Register'!A:D,4,0),0) -> 0 | D14: =IFERROR(VLOOKUP(A14,'🏘️ Flat Register'!A:F,6,0),0) -> 0 | E14: =IFERROR(VLOOKUP(A14,'🏘️ Flat Register'!A:H,8,0),0) -> 0 | F14: =IFERROR(VLOOKUP(A14,'🏘️ Flat Register'!A:L,9,0),"") | G14: =IFERROR(VLOOKUP(A14,'🏘️ Flat Register'!A:N,11,0),"") | H14: =IFERROR(VLOOKUP(A14,'🏘️ Flat Register'!A:O,12,0),"") | I14: =IFERROR(SUMIF('💳 PAYMENTS Entery'!G:G,A14,'💳 PAYMENTS Entery'!H:H),0) -> 0 | J14: =IFERROR(E14-I14,0) -> 0 | K14: =IFERROR(I14/E14,0) -> 0
A15: F-302 | B15: =IFERROR(VLOOKUP(A15,'🏘️ Flat Register'!A:C,3,0),"") | C15: =IFERROR(VLOOKUP(A15,'🏘️ Flat Register'!A:D,4,0),0) -> 0 | D15: =IFERROR(VLOOKUP(A15,'🏘️ Flat Register'!A:F,6,0),0) -> 0 | E15: =IFERROR(VLOOKUP(A15,'🏘️ Flat Register'!A:H,8,0),0) -> 0 | F15: =IFERROR(VLOOKUP(A15,'🏘️ Flat Register'!A:L,9,0),"") | G15: =IFERROR(VLOOKUP(A15,'🏘️ Flat Register'!A:N,11,0),"") | H15: =IFERROR(VLOOKUP(A15,'🏘️ Flat Register'!A:O,12,0),"") | I15: =IFERROR(SUMIF('💳 PAYMENTS Entery'!G:G,A15,'💳 PAYMENTS Entery'!H:H),0) -> 0 | J15: =IFERROR(E15-I15,0) -> 0 | K15: =IFERROR(I15/E15,0) -> 0
A16: F-401 | B16: =IFERROR(VLOOKUP(A16,'🏘️ Flat Register'!A:C,3,0),"") | C16: =IFERROR(VLOOKUP(A16,'🏘️ Flat Register'!A:D,4,0),0) -> 0 | D16: =IFERROR(VLOOKUP(A16,'🏘️ Flat Register'!A:F,6,0),0) -> 0 | E16: =IFERROR(VLOOKUP(A16,'🏘️ Flat Register'!A:H,8,0),0) -> 0 | F16: =IFERROR(VLOOKUP(A16,'🏘️ Flat Register'!A:L,9,0),"") | G16: =IFERROR(VLOOKUP(A16,'🏘️ Flat Register'!A:N,11,0),"") | H16: =IFERROR(VLOOKUP(A16,'🏘️ Flat Register'!A:O,12,0),"") | I16: =IFERROR(SUMIF('💳 PAYMENTS Entery'!G:G,A16,'💳 PAYMENTS Entery'!H:H),0) -> 0 | J16: =IFERROR(E16-I16,0) -> 0 | K16: =IFERROR(I16/E16,0) -> 0
A17: F-402 | B17: =IFERROR(VLOOKUP(A17,'🏘️ Flat Register'!A:C,3,0),"") | C17: =IFERROR(VLOOKUP(A17,'🏘️ Flat Register'!A:D,4,0),0) -> 0 | D17: =IFERROR(VLOOKUP(A17,'🏘️ Flat Register'!A:F,6,0),0) -> 0 | E17: =IFERROR(VLOOKUP(A17,'🏘️ Flat Register'!A:H,8,0),0) -> 0 | F17: =IFERROR(VLOOKUP(A17,'🏘️ Flat Register'!A:L,9,0),"") | G17: =IFERROR(VLOOKUP(A17,'🏘️ Flat Register'!A:N,11,0),"") | H17: =IFERROR(VLOOKUP(A17,'🏘️ Flat Register'!A:O,12,0),"") | I17: =IFERROR(SUMIF('💳 PAYMENTS Entery'!G:G,A17,'💳 PAYMENTS Entery'!H:H),0) -> 0 | J17: =IFERROR(E17-I17,0) -> 0 | K17: =IFERROR(I17/E17,0) -> 0
A18: F-500 | B18: =IFERROR(VLOOKUP(A18,'🏘️ Flat Register'!A:C,3,0),"") | C18: =IFERROR(VLOOKUP(A18,'🏘️ Flat Register'!A:D,4,0),0) -> 0 | D18: =IFERROR(VLOOKUP(A18,'🏘️ Flat Register'!A:F,6,0),0) -> 0 | E18: =IFERROR(VLOOKUP(A18,'🏘️ Flat Register'!A:H,8,0),0) -> 0 | F18: =IFERROR(VLOOKUP(A18,'🏘️ Flat Register'!A:L,9,0),"") | G18: =IFERROR(VLOOKUP(A18,'🏘️ Flat Register'!A:N,11,0),"") | H18: =IFERROR(VLOOKUP(A18,'🏘️ Flat Register'!A:O,12,0),"") | I18: =IFERROR(SUMIF('💳 PAYMENTS Entery'!G:G,A18,'💳 PAYMENTS Entery'!H:H),0) -> 0 | J18: =IFERROR(E18-I18,0) -> 0 | K18: =IFERROR(I18/E18,0) -> 0

Sheet 🔍 Audit Trail
A1: 🔍 Audit Trail — Log all changes manually here for compliance
A2: N
A3: Entry ID | B3: Timestamp | C3: User | D3: Sheet | E3: Record ID | F3: Action | G3: Field | H3: Old Value | I3: New Value | J3: IP | K3: Notes
A4: AT-001 | B4: 2026-06-01 09:00 | C4: admin | D4: 💳 PAYMENTS | E4: R-001 | F4: INSERT | G4: Amount | H4: – | I4: 500,000 | J4: 192.168.1.10 | K4: Payment entered
A5: AT-002 | B5: 2026-06-02 10:15 | C5: admin | D5: 💳 PAYMENTS | E5: R-002 | F5: INSERT | G5: Amount | H5: – | I5: 1,000,000 | J5: 192.168.1.10 | K5: Payment entered
A6: AT-003 | B6: 2026-06-03 11:00 | C6: admin | D6: 🧾 EXPENSES | E6: PV-001 | F6: INSERT | G6: Amount | H6: – | I6: 250,000 | J6: 192.168.1.10 | K6: Expense entered
A7: AT-004 | B7: 2026-06-05 09:30 | C7: admin | D7: 🧾 EXPENSES | E7: PV-002 | F7: INSERT | G7: Amount | H7: – | I7: 100,000 | J7: 192.168.1.10 | K7: Expense entered
A8: AT-005 | B8: 2026-06-05 12:00 | C8: admin | D8: 🏘️ Flat Master | E8: F-104 | F8: UPDATE | G8: Status | H8: Available | I8: Hold | J8: 192.168.1.10 | K8: Reserved VIP

Sheet 🧾 EXPENSES ← Enter Here
A1: 🧾 EXPENSES ← Enter Here — ONE ROW = Bank/Cash/GL/P&L/Balance Sheet ALL Update
A2: Voucher No auto | Bank/Cash auto-deducts | GL auto-posts | P&L auto-updates | Dashboard auto-updates
A3: ⚡ ENTER ONE ROW HERE. You do NOT need to update Bank Book, Cash Book, General Ledger, Trial Balance, P&L or Balance Sheet — they all read from this sheet automatically.
A4: Total Expenses | F4: Construction | K4: Admin & Other | P4: This Month
A5: =SUM(J8:J50000) -> 4060000 | F5: =IFERROR(SUMIF(E8:E50000,"Material",J8:J50000)+SUMIF(E8:E50000,"Labor",J8:J50000)+SUMIF(E8:E50000,"Contractor",J8:J50000),0) -> 0 | K5: =IFERROR(SUMIF(E8:E50000,"Admin",J8:J50000)+SUMIF(E8:E50000,"Other",J8:J50000),0) -> 4060000 | P5: =SUMPRODUCT((MONTH(C8:C5000)=MONTH(TODAY()))*(YEAR(C8:C5000)=YEAR(TODAY()))*J8:J5000) -> #VALUE!
A7: ▌ DATA ENTRY ZONE — Enter ONE row per expense. All other sheets update automatically.
A8: Voucher No. [AUTO] | B8: Serial [ENTER 1,2,3] | C8: Date [ENTER] | D8: Project ID [ENTER] | E8: Category [ENTER] | F8: Sub-Category [ENTER] | G8: Vendor/Payee [ENTER] | H8: Paid From [ENTER] | I8: Gross Amt [ENTER] | J8: Net Amt [ENTER=same if no tax] | K8: Tax [ENTER] | L8: Cheque/TT [ENTER] | M8: Approved By [ENTER] | N8: Notes [ENTER]
A9: ↓ Voucher No. auto-generates as PV-001, PV-002 etc. | Paid From drives Bank or Cash deduction | Category drives P&L categorisation
A11: =IF(B11<>"","PV-"&TEXT(B11,"000"),"") -> PV-001 | B11: 1 | C11: 2026-06-03 | D11: PRJ-001 | E11: Other | F11: Asset | G11: Property Owner | H11: HBL | I11: 2000000 | J11: 2000000 | K11: 0 | L11: CHQ-5001 | M11: sharjeel | N11: Plot Purchase
A12: =IF(B12<>"","PV-"&TEXT(B12,"000"),"") -> PV-002 | B12: 2 | C12: 2026-06-03 | D12: PRJ-001 | E12: Other | F12: Asset | G12: Property Owner | H12: HBL | I12: 2000000 | J12: 2000000 | K12: 0 | L12: CHQ-5001 | M12: sharjeel | N12: Plot Purchase
A13: =IF(B13<>"","PV-"&TEXT(B13,"000"),"") -> PV-003 | B13: 3 | C13: 2026-06-03 | E13: Other | F13: Commission | G13: commission | H13: Cash | I13: 60000 | J13: 60000 | K13: 0 | L13: cash | M13: sharjeel | N13: Plot Purchase

Sheet 📋 Pay Plans
A1: 📋 PAYMENT PLAN TEMPLATES
A2: Define once. Select in Flat Master.
A3: Plan ID | B3: Plan Name | C3: Type | D3: Down % | E3: No. Inst. | F3: Frequency | G3: Possession % | H3: Notes
A4: PLN-001 | B4: Monthly-18 | C4: Monthly | D4: 0.2 | E4: 18 | F4: Monthly | G4: 0.1 | H4: 20% down + 18 monthly + 10% possession
A5: PLN-002 | B5: Quarterly-12 | C5: Quarterly | D5: 0.25 | E5: 12 | F5: Quarterly | G5: 0.1 | H5: 25% down + 12 quarterly + 10% possession
A6: PLN-003 | B6: Half-Yearly-6 | C6: Half-Yearly | D6: 0.3 | E6: 6 | F6: Half-Yearly | G6: 0.1 | H6: 30% down + 6 half-yearly + 10% possession
A7: PLN-004 | B7: Milestone-5 | C7: Construction | D7: 0.2 | E7: 5 | F7: Milestone | G7: 0.2 | H7: 20% booking + 5 milestones + 20% possession
A8: PLN-005 | B8: Cash-Full | C8: Cash | D8: 1 | E8: 1 | F8: Lump Sum | G8: 0 | H8: Full cash (discount applicable)

Sheet Sheet1

Sheet 💧 Cash Flow AUTO
A1: 💧 Cash Flow AUTO — Period Ending 15 July 2026 | DO NOT ENTER DATA
A2: I
A3: OPERATING ACTIVITIES
A4: Collections from Customers | H4: =SUM('💳 PAYMENTS Entery'!H11:H49967) -> 2580000
A5: Material | H5: =-IFERROR(SUMIF('🧾 EXPENSES ← Enter Here'!E:E,"Material",'🧾 EXPENSES ← Enter Here'!J:J),0) -> 0
A6: Labor | H6: =-IFERROR(SUMIF('🧾 EXPENSES ← Enter Here'!E:E,"Labor",'🧾 EXPENSES ← Enter Here'!J:J),0) -> 0
A7: Admin & Overhead | H7: =-IFERROR(SUMIF('🧾 EXPENSES ← Enter Here'!E:E,"Admin",'🧾 EXPENSES ← Enter Here'!J:J),0) -> 0
A8: Other Expenses | H8: =-IFERROR(SUMIF('🧾 EXPENSES ← Enter Here'!E:E,"Other",'🧾 EXPENSES ← Enter Here'!J:J),0) -> -4060000
A9: NET OPERATING CASH FLOW | H9: =SUM(H4:H8) -> -1480000
A11: INVESTING ACTIVITIES
A12: Fixed Asset Purchases | H12: 0
A13: Asset Sales | H13: 0
A14: NET INVESTING CASH FLOW | H14: =SUM(H12:H13) -> 0
A16: FINANCING ACTIVITIES
A17: Partner Capital | H17: =IFERROR(SUM('👥 Partners'!F8:F12),0) -> 2000000
A18: Partner Withdrawals | H18: =-IFERROR(SUM('👥 Partners'!I8:I12),0) -> 0
A19: NET FINANCING CASH FLOW | H19: =SUM(H17:H18) -> 2000000
A21: SUMMARY
A22: Opening Balance | H22: 0
A23: Net Cash Flow | H23: =H9+H14+H19 -> 520000
A24: CLOSING CASH BALANCE | H24: =H22+H23 -> 520000
